Workbook
Name \a: [1]bobudget!#REF!
Name \b: [1]bobudget!#REF!
Name \c: [1]bobudget!#REF!
Name \l: [2]main!#REF!
Name \m: #N/A
Name \q: #N/A
Name ______MAT1: #REF!
Name ______MAT2: #REF!
Name ______MAT3: #REF!
Name ______p24500: #REF!
Name ______ROW2: [1]bobudget!#REF!
Name ______WIP1: #REF!
Name ______WIP2: #REF!
Name _____MAT1: #REF!
Name _____MAT2: #REF!
Name _____MAT3: #REF!
Name _____p24500: #REF!
Name _____ROW2: [1]bobudget!#REF!
Name _____WIP1: #REF!
Name _____WIP2: #REF!
Name ____MAT1: #REF!
Name ____MAT2: #REF!
Name ____MAT3: #REF!
Name ____p24500: #REF!
Name ____ROW2: [1]bobudget!#REF!
Name ____WIP1: #REF!
Name ____WIP2: #REF!
Name ___MAT1: #REF!
Name ___MAT2: #REF!
Name ___MAT3: #REF!
Name ___p24500: #REF!
Name ___ROW2: [3]bobudget!#REF!
Name ___WIP1: #REF!
Name ___WIP2: #REF!
Name __123Graph_A_1: '[4]119'!#REF!
Name __123Graph_A_2: '[5]119'!#REF!
Name __123Graph_A_3: '[5]119'!#REF!
Name __123Graph_A_4: '[4]119'!#REF!
Name __123Graph_B_1: '[4]119'!#REF!
Name __123Graph_B_2: '[5]119'!#REF!
Name __123Graph_B_3: '[5]119'!#REF!
Name __123Graph_B_4: '[4]119'!#REF!
Name __123Graph_C_1: '[4]119'!#REF!
Name __123Graph_C_2: '[5]119'!#REF!
Name __123Graph_C_3: '[5]119'!#REF!
Name __123Graph_C_4: '[4]119'!#REF!
Name __123Graph_X_1: '[4]119'!#REF!
Name __123Graph_X_2: '[5]119'!#REF!
Name __123Graph_X_3: '[5]119'!#REF!
Name __123Graph_X_4: '[4]119'!#REF!
Name __MAT1: #REF!
Name __MAT2: #REF!
Name __MAT3: #REF!
Name __p24500: #REF!
Name __ROW2: [1]bobudget!#REF!
Name __WIP1: #REF!
Name __WIP2: #REF!
Name _1: #REF!
Name _1_1: #REF!
Name _1_2: #REF!

Sheet PQ Audit Checklist
B1: VINFAST PQ/GD&T Gateway audit
G2: LH800 | H2: VF6 | I2: VF6NP
B3: Module | C3: Sub Module | D3: PQ Criteria | E3: Check Item | F3: Evaluation Guide | G3: score | H3: Sore | I3: Score | J3: BM1 Commnet | K3: BM2 Comment | L3: JIRA | M3: BM Row Average | N3: VF6 Row Average | O3: VF6NP Row Average
B4: Exterior | C4: Body | D4: Fit & Finish | E4: Panel gaps, flushness and line alignment | F4: View panel joints from the front, side and an angle. Check uneven gaps, panel height differences and broken styling lines. Measure specified points against DTS. | G4: 6 | H4: 5 | I4: 5 | K4: Carryover design/paint quality | M4: =AVERAGE(G4:G9) -> 6 | N4: =AVERAGE(H4:H9) -> 5.6666667 | O4: =AVERAGE(I4:I9) -> 5.6666667
D5: Aesthetics | E5: Painted surface quality | F5: Check panels in daylight and inspection lighting. Look for dents, waves, paint runs, rough paint texture and dirt trapped in paint. | G5: 6 | H5: 6 | I5: 6 | K5: Balanced / Clean / Calm
D6: Touch & Feel | E6: Surface feel and scratch resistance | F6: Check normal contact areas for rough surfaces and unfinished edges. Inspect paint scratches before and after approved use and cleaning tests. Refer sharp-edge concerns to Safety. | G6: 6 | H6: 5 | I6: 5 | K6: Acceptable / Basic / Lacking refinement
D7: Functionality | E7: Body clearance during use | F7: Open adjacent closures and check loading and cleaning access. Look for rubbing, catching or blocked access. | G7: 6 | H7: 6 | I7: 6 | K7: intuitive / Low friction
D8: Sound Quality | E8: Body creak and rattle | F8: Listen during the approved road test. Record where creaks or rattles occur, the speed and road condition. Confirm the noise source. | G8: 6 | H8: 6 | I8: 6 | K8: Clean / Clear / Moderate richness / Controlled
D9: Harmony & Authenticity | E9: Body design continuity | F9: View the whole vehicle from the front, side and rear. Compare styling lines, panel transitions and intended left/right balance with the approved design. | G9: 6 | H9: 6 | I9: 6 | K9: Harmonized / Genuine-leaning / Mostly coherent
C10: Doors & Closures | D10: Fit & Finish | E10: Closure gaps, flushness and seals | F10: Fully close doors, bonnet and tailgate. Check gaps, panel height differences, corner alignment and seal seating. Recheck after opening and closing. | G10: 5 | H10: 5 | I10: 5 | K10: Carryover door design | M10: =AVERAGE(G10:G15) -> 6 | N10: =AVERAGE(H10:H15) -> 5.5 | O10: =AVERAGE(I10:I15) -> 5.8333333
D11: Aesthetics | E11: Closure surfaces and hardware | F11: Check closures open and closed. Look for dents, paint defects, exposed sealant and poorly finished visible fasteners. | G11: 7 | H11: 6 | I11: 7 | K11: Door handle new design
D12: Touch & Feel | E12: Handle feel and scratch resistance | F12: Grip handles and operate releases. Check comfort, rough edges and looseness. Inspect handles and recesses for scratches after approved use and cleaning tests. | G12: 6 | H12: 5 | I12: 5 | K12: Door handle new design/ poor door closing
D13: Functionality | E13: Opening, closing and latching | F13: Open and close each closure using the specified method. Check smooth movement, operating effort, hold-open function and full latching. | G13: 6 | H13: 6 | I13: 7 | K13: VF6 legacy mud inturusion improved
D14: Sound Quality | E14: Opening and closing sound | F14: Listen while releasing, opening and closing each closure. Check squeaks, metallic ringing, repeated impacts and vibration after closing. | G14: 6 | H14: 5 | I14: 5 | K14: carryover door design/Poor door closing sound
D15: Harmony & Authenticity | E15: Closure feel and finish consistency | F15: Compare handles and visible hardware across the vehicle. Check consistent finishes, operating feel and closing sounds where the same experience is intended. | G15: 6 | H15: 6 | I15: 6 | K15: Harmonized / Genuine-leaning / Mostly coherent
C16: Lighting | D16: Fit & Finish | E16: Lamp installation and alignment | F16: Check lamp-to-body and lamp-to-bumper joints. Look for uneven gaps, incorrect panel height and misaligned internal elements. Compare left and right lamps. | G16: 6 | H16: 5 | I16: 7 | K16: New design. DTS improved | M16: =AVERAGE(G16:G21) -> 6 | N16: =AVERAGE(H16:H21) -> 5.8333333 | O16: =AVERAGE(I16:I21) -> 6.5
D17: Aesthetics | E17: Lens and illuminated appearance | F17: Check lamps off and on in daylight and darkness. Look for lens defects, internal dirt, bright spots, dark areas and unintended colour differences. | G17: 6 | H17: 6 | I17: 7 | K17: New design.
D18: Touch & Feel | E18: Lens finish and scratch resistance | F18: Check accessible lens and trim edges for roughness or looseness. Inspect scratches and haze before and after approved cleaning tests. Review the approved scratch-test results. | G18: 6 | H18: 6 | I18: 6 | K18: solid design. RPS/Datum implemented/No ahrp edge
D19: Functionality | E19: Lighting modes and response | F19: Switch on each applicable lighting mode. Check correct activation, sequence and flicker. Report failures to Lighting Engineering for further assessment. | G19: 6 | H19: 6 | I19: 6 | K19: New design LED/projection lamp
D20: Sound Quality | E20: Lamp operating noise | F20: In a quiet area, operate fitted lamp motors or adjustment functions. Listen for buzzing, chatter or repeated cycling. Mark N/A if no audible mechanism is fitted. | G20: 6 | H20: 6 | I20: 6 | K20: solid design. RPS/Datum implemented
D21: Harmony & Authenticity | E21: Lighting design consistency | F21: View front and rear lighting together with the vehicle design. Check light shapes, intended symmetry and colour against the approved design. | G21: 6 | H21: 6 | I21: 7 | K21: new design improved harmony with surounding part
C22: Glass & Wiper | D22: Fit & Finish | E22: Glass, mouldings and parked wipers | F22: Check glass edges, surrounding mouldings and parked wipers. Look for uneven seating, open corner joints, exposed adhesive and incorrect parking position. | G22: 6 | H22: 5 | I22: 5 | K22: Carryover design/ poor trim fitmenent | M22: =AVERAGE(G22:G27) -> 5.6666667 | N22: =AVERAGE(H22:H27) -> 5.6666667 | O22: =AVERAGE(I22:I27) -> 5.6666667
D23: Aesthetics | E23: Glass clarity and finish | F23: Look through the glass from normal seating positions. Check scratches, haze and distorted views. Inspect the black border and surrounding trim from outside. | G23: 5 | H23: 5 | I23: 5 | K23: Carryover design/ exposed wisher line
D24: Touch & Feel | E24: Contact finish and scratch resistance | F24: Check accessible trim and blade-service areas for rough edges. Inspect glass and trim scratches after approved wiping and cleaning tests. Disable wipers before service-contact checks. | G24: 6 | H24: 6 | I24: 6 | K24: Carryover design
D25: Functionality | E25: Wiping, washing and parking | F25: Wet the glass and operate each wiper mode and washer. Check missed areas, streaks, spray coverage and correct parking. | G25: 5 | H25: 6 | I25: 6 | K25: Carryover design/ unclean area remained
D26: Sound Quality | E26: Wiper noise | F26: Listen while wiping wet glass at each specified speed. Check squeal, blade chatter, motor noise and impacts at reversal or parking. | G26: 6 | H26: 6 | I26: 6 | K26: Carryover design
D27: Harmony & Authenticity | E27: Glass surround integration | F27: View glass mouldings, pillars, cowl and parked wipers together. Check aligned transitions and finishes against the approved design. | G27: 6 | H27: 6 | I27: 6 | K27: Carryover design
C28: Exterior Trim | D28: Fit & Finish | E28: Trim seating and joints | F28: Check grilles, badges, garnish and cladding. Look for uneven gaps, lifted corners and exposed clips. Check attachment using the approved method. | G28: 6 | H28: 5 | I28: 7 | K28: new design improved DTS/RPS/Location strategy | M28: =AVERAGE(G28:G33) -> 6 | N28: =AVERAGE(H28:H33) -> 5.5 | O28: =AVERAGE(I28:I33) -> 6.3333333
D29: Aesthetics | E29: Trim surface finish | F29: Check visible trim for dents, moulding marks, scratches and coating defects. Compare colour, gloss and surface pattern with approved samples. | G29: 6 | H29: 6 | I29: 7 | K29: new design improved DTS
D30: Touch & Feel | E30: Trim feel and scratch resistance | F30: Touch normal contact areas. Check texture, rough edges and looseness. Inspect scratches and scuffs after approved handling and cleaning tests. | G30: 6 | H30: 5 | I30: 6 | K30: Mostly solid/ no sharp edges on A surface
D31: Functionality | E31: Movable trim and access | F31: Operate fitted movable trim. Check smooth movement and access for normal use and cleaning. Mark operating effort N/A for fixed decorative parts. | G31: 6 | H31: 6 | I31: 6 | K31: Reliable
D32: Sound Quality | E32: Trim squeak and rattle | F32: Listen during normal use and the approved road test. Locate trim squeaks or rattles and record the conditions. | G32: 6 | H32: 5 | I32: 6 | K32: solid design. RPS/Datum implemented
D33: Harmony & Authenticity | E33: Trim colour and material harmony | F33: Compare neighbouring painted, plated and textured parts. Check colour, gloss, badge alignment and material appearance against approved samples. | G33: 6 | H33: 6 | I33: 6 | K33: well integrated panel matching with trim
C34: Wheel/Wheel cover /Rim | D34: Fit & Finish | E34: Cover and centre-cap seating | F34: Check wheel covers and centre caps around their edges. Look for uneven seating, open gaps and poor alignment. Check valve access. | G34: 6 | H34: 6 | I34: 6 | K34: new design improved DTS | M34: =AVERAGE(G34:G39) -> 6 | N34: =AVERAGE(H34:H39) -> 6 | O34: =AVERAGE(I34:I39) -> 6.3333333
D35: Aesthetics | E35: Wheel finish | F35: Check wheel faces, recesses and visible fasteners. Look for scratches, paint defects, machining marks and unintended colour differences. | G35: 6 | H35: 6 | I35: 7 | K35: new design improved DTS
D36: Touch & Feel | E36: Edge finish and scratch resistance | F36: Check normal handling areas for rough edges. Inspect scratches after approved cleaning and cover-handling tests. Record tool damage separately. | G36: 6 | H36: 6 | I36: 6 | K36: Mostly solid/ no sharp edges on A surface
D37: Functionality | E37: Valve access and cover operation | F37: Check access for tyre inflation. Remove and refit covers or caps only by the approved procedure. Confirm correct seating and retention. | G37: 6 | H37: 6 | I37: 6 | K37: Reliable
D38: Sound Quality | E38: Cover and cap rattle | F38: Listen during the approved road test. Check cover or cap rattle. Confirm the source is not the tyre, brake or bearing. | G38: 6 | H38: 6 | I38: 6 | K38: solid design. RPS/Datum implemented
D39: Harmony & Authenticity | E39: Wheel design and vehicle match | F39: View the wheels with the complete vehicle. Check wheel design, finish, caps and visible hardware against the approved variant specification. | G39: 6 | H39: 6 | I39: 7 | K39: well integrated wheel design with exterior
B40: Interior | C40: Instrument Panel | D40: Fit & Finish | E40: IP joints and alignment | F40: Sit in the driver and passenger seats. Check joints around doors, displays, vents and trim. Look for uneven gaps and panel height differences. | G40: 7 | H40: 5 | I40: 8 | K40: new design. DTS/RPS/datum imrpoved | M40: =AVERAGE(G40:G45) -> 7 | N40: =AVERAGE(H40:H45) -> 5.5 | O40: =AVERAGE(I40:I45) -> 8
D41: Aesthetics | E41: IP finish and reflections | F41: Check the IP in daylight and cabin lighting. Look for surface defects and colour differences. Record windshield reflections from the specified driver positions. | G41: 7 | H41: 5 | I41: 8 | K41: new design
D42: Touch & Feel | E42: IP feel and scratch resistance | F42: Touch normal contact areas. Check texture, padding, rough edges and looseness. Inspect scratches and scuffs after approved contact and cleaning tests. | G42: 8 | H42: 6 | I42: 8 | K42: soft touch IP top cover with chrome finisher
D43: Functionality | E43: Glovebox and storage operation | F43: Open and close the glovebox and fitted storage lids. Check reach, effort, controlled movement, latching and interference with intended contents. | G43: 7 | H43: 5 | I43: 8 | K43: Glove box volume increase.
D44: Sound Quality | E44: IP and glovebox noise | F44: Listen during glovebox operation and the approved road test. Check creaks, rattles and harsh lid or latch impacts. | G44: 6 | H44: 6 | I44: 8 | K44: soft touch IP top cover
D45: Harmony & Authenticity | E45: IP and cabin design continuity | F45: Compare the IP with the console and door trims. Check colour, surface pattern, stitching and decorative-line continuity against approved samples. | G45: 7 | H45: 6 | I45: 8 | K45: Good integration with IP vs Door trim
C46: Steering Wheel | D46: Fit & Finish | E46: Wheel trim and seam fit | F46: From the driver seat, check switch surrounds, spoke trim and rim seams. Look for uneven joints, poor stitching and loose trim. Do not probe airbag interfaces. | G46: 7 | H46: 7 | I46: 8 | K46: New design Carry over from VF7NP | M46: =AVERAGE(G46:G51) -> 7 | N46: =AVERAGE(H46:H51) -> 6.5 | O46: =AVERAGE(I46:I51) -> 7.3333333
D47: Aesthetics | E47: Wheel covering and graphics | F47: Check the rim, hub and buttons. Look for wrinkles, uneven seams, coating defects and unclear or misaligned graphics. | G47: 7 | H47: 7 | I47: 7 | K47: New design/ competitive with BYD dolphin
D48: Touch & Feel | E48: Grip feel and scratch resistance | F48: Hold the wheel at normal grip positions. Check texture, seam comfort and button feel. Inspect scratches and finish wear after approved use and cleaning tests. | G48: 7 | H48: 7 | I48: 7 | K48: new CMF/ leather cover/ improved size
D49: Functionality | E49: Controls and adjustment | F49: Operate buttons, scroll wheels and fitted adjustment controls. Check reach, correct response and accidental activation. | G49: 7 | H49: 6 | I49: 8 | K49: Adding wheel control switch packs/ steering wheel stalks
D50: Sound Quality | E50: Control and trim sound | F50: In a quiet cabin, operate each control. Listen for inconsistent clicks or loose-part noise. Check trim noise during normal steering use. | G50: 6 | H50: 6 | I50: 6 | K50: New design
D51: Harmony & Authenticity | E51: Wheel and cockpit consistency | F51: Compare wheel finishes, symbols and button feedback with other cabin controls. Check consistency with the approved cockpit design. | G51: 8 | H51: 6 | I51: 8 | K51: New design harmony with interior design
C52: Console | D52: Fit & Finish | E52: Console joints and lids | F52: Check console joints and lids open and closed. Look for uneven gaps and panel height differences. Check interference at the specified seat positions. | G52: 7 | H52: 5 | I52: 8 | K52: new design. DTS/RPS/datum imrpoved | M52: =AVERAGE(G52:G57) -> 7 | N52: =AVERAGE(H52:H57) -> 5.3333333 | O52: =AVERAGE(I52:I57) -> 7.5
D53: Aesthetics | E53: Console and storage finish | F53: Check decorative surfaces, cupholders and storage interiors. Look for scratches, moulding marks, coating defects and poorly finished visible hardware. | G53: 7 | H53: 6 | I53: 8 | K53: new design
D54: Touch & Feel | E54: Contact feel and scratch resistance | F54: Check armrests and hand-contact areas for comfort, texture and looseness. Inspect scratches after approved item-contact and cleaning tests. | G54: 7 | H54: 5 | I54: 7 | K54: Arm rest soft cover
D55: Functionality | E55: Storage, cupholders and armrest | F55: Use the specified cups, bottles and items. Check insertion, retention and removal. Operate lids, armrests and fitted charging functions. | G55: 8 | H55: 5 | I55: 8 | K55: wirless charger/ more storage space/cup holders
D56: Sound Quality | E56: Console and stored-item noise | F56: Operate lids and armrests, then road-test with specified stored items. Identify whether noise comes from the mechanism, trim or stored items. | G56: 6 | H56: 5 | I56: 6 | K56: solid design. RPS/Datum implemented
D57: Harmony & Authenticity | E57: Console and cabin consistency | F57: Compare console finishes and lines with the IP and seats. Check related controls for consistent graphics and operating feel. | G57: 7 | H57: 6 | I57: 8 | K57: New design harmony with interior design
C58: Door Trim | D58: Fit & Finish | E58: Door-trim seating and alignment | F58: Check handles, switches, speaker grilles and trim edges. Close the door and check alignment with the IP. Look for uneven joints and lifted trim. | G58: 7 | H58: 5 | I58: 8 | K58: new design. DTS/RPS/datum imrpoved | M58: =AVERAGE(G58:G63) -> 7.1666667 | N58: =AVERAGE(H58:H63) -> 5.5 | O58: =AVERAGE(I58:I63) -> 7.5
D59: Aesthetics | E59: Door-trim finish | F59: Check from normal seating positions and with the door open. Look for wrinkles, moulding marks, adhesive traces, poor stitching and colour differences. | G59: 8 | H59: 6 | I59: 8 | K59: new design Harmonious / Stylish / Confident
D60: Touch & Feel | E60: Contact comfort and scratch resistance | F60: Check armrests, pull handles and switches for comfort, texture and looseness. Inspect recesses and pocket edges for scratches after approved use and cleaning tests. | G60: 7 | H60: 6 | I60: 7 | K60: Arm rest soft cover
D61: Functionality | E61: Controls and pocket usability | F61: Operate door releases, window and mirror controls. Check reach, hand clearance and accidental activation. Use specified items to check pocket access and retention. | G61: 7 | H61: 5 | I61: 8 | K61: Door pull cup design/easy access of switchs
D62: Sound Quality | E62: Door-trim and speaker noise | F62: Listen during door closing, road driving and audio playback. Check trim creaks, pocket rattles and speaker-grille buzz. Confirm the source. | G62: 6 | H62: 5 | I62: 6 | K62: solid design. RPS/Datum implemented
D63: Harmony & Authenticity | E63: Door and cabin design continuity | F63: Compare door trims with the IP, console and seats. Check lines, colours, materials and control symbols, allowing approved front/rear differences. | G63: 8 | H63: 6 | I63: 8 | K63: New design harmony with interior design
C64: Seats | D64: Fit & Finish | E64: Seat covers, seams and trim | F64: Check seams, cover tension, headrest joints and plastic trim. Move the seat through normal positions. Look for misalignment, loose parts and interference. | G64: 7 | H64: 6 | I64: 8 | K64: New design. DTS/RPS/datum imrpoved | M64: =AVERAGE(G64:G69) -> 7.3333333 | N64: =AVERAGE(H64:H69) -> 6 | O64: =AVERAGE(I64:I69) -> 7.5
D65: Aesthetics | E65: Seat-cover appearance | F65: Check seats before and after the specified sitting test. Look for wrinkles, uneven stitching, misaligned perforations and colour differences. Apply the specified recovery time. | G65: 8 | H65: 6 | I65: 8 | K65: new design Harmonious / Stylish / Confident
D66: Touch & Feel | E66: Seat comfort and surface damage | F66: Sit in the seat and check texture, seam pressure and support. Inspect plastic scratches after approved entry, exit and cleaning tests. Review upholstery wear-test results separately. | G66: 8 | H66: 7 | I66: 7 | K66: leather PU cover/ fabric
D67: Functionality | E67: Adjustment and comfort features | F67: Operate fitted adjustments, folding and comfort features. Check reach, smooth movement, correct response and interference. Refer locking concerns to Seat Engineering. | G67: 7 | H67: 5 | I67: 8 | K67: Rear Seat thigh support imroved/ seat back reclining angle imroved
D68: Sound Quality | E68: Seat movement and adjustment noise | F68: Listen during adjustment, occupant movement and the approved road test. Check motor noise, squeaks and rattles. Record seat position and occupant loading. | G68: 6 | H68: 6 | I68: 6 | K68: solid design. RPS/Datum implemented
D69: Harmony & Authenticity | E69: Seat and cabin material consistency | F69: Compare all seat rows with the cabin design. Check materials, stitching and decorative details against the approved specification. | G69: 8 | H69: 6 | I69: 8 | K69: New design harmony with interior design
C70: HVAC | D70: Fit & Finish | E70: Vent and control-panel fit | F70: Check vents and control-panel joints. Move vent blades through their range. Look for uneven gaps, misaligned blades and poorly seated parts. | G70: 7 | H70: 6 | I70: 8 | K70: New design. DTS/RPS/datum imrpoved | M70: =AVERAGE(G70:G75) -> 7.1666667 | N70: =AVERAGE(H70:H75) -> 5.8333333 | O70: =AVERAGE(I70:I75) -> 7.5
D71: Aesthetics | E71: Vent and control appearance | F71: View vents and controls from normal seating positions. Check surface defects, graphics, illumination and unwanted visibility of internal hardware. | G71: 7 | H71: 6 | I71: 8 | K71: new design Harmonious / Stylish / Confident
D72: Touch & Feel | E72: Control feel and scratch resistance | F72: Move vent tabs and operate knobs and buttons. Check grip, resistance, clicks and looseness. Inspect scratches and worn graphics after approved operation and cleaning tests. | G72: 7 | H72: 5 | I72: 7 | K72: Carry over air vent design from VF7NP
D73: Functionality | E73: Airflow and control response | F73: Select the specified fan speeds and modes. Adjust and close vents. Check airflow direction, control response and ease of use. | G73: 7 | H73: 6 | I73: 7 | K73: Carry over air vent design from VF7NP
D74: Sound Quality | E74: Airflow and motor noise | F74: In a quiet cabin, test specified fan speeds and modes. Listen for whistles, buzzing, vibration and repeated actuator clicking. | G74: 7 | H74: 6 | I74: 7 | K74: Carry over air vent design from VF7NP
D75: Harmony & Authenticity | E75: HVAC control consistency | F75: Compare HVAC finishes, symbols and illumination with other controls. Check that physical controls and screen controls show consistent functions and states. | G75: 8 | H75: 6 | I75: 8 | K75: new design/ harmony with IP interior with chrome finish
C76: Infotainment | D76: Fit & Finish | E76: Display and control fit | F76: Check display edges, bezel joints and controls. Look for uneven gaps, misalignment and movement during normal touch operation. | G76: 8 | H76: 6 | I76: 8 | K76: DTS/RPS/datum imrpoved | M76: =AVERAGE(G76:G81) -> 6.8333333 | N76: =AVERAGE(H76:H81) -> 5.8333333 | O76: =AVERAGE(I76:I81) -> 6.3333333
D77: Aesthetics | E77: Display clarity and finish | F77: Check the screen in daylight and darkness from specified seating positions. Look for unreadable content, strong reflections, pixel defects and uneven brightness. | G77: 7 | H77: 6 | I77: 6 | K77: carryover from Limo
D78: Touch & Feel | E78: Touch feel and scratch resistance | F78: Tap and swipe the screen and operate physical controls. Check response and feedback. Inspect scratches, haze and coating wear after approved contact and cleaning tests. | G78: 6 | H78: 6 | I78: 6 | K78: carryover from Limo
D79: Functionality | E79: Customer tasks and response | F79: Follow the approved tasks for media, navigation, phone connection and settings. Check completion, delays, errors and recovery. Record the software version. | G79: 7 | H79: 5 | I79: 6 | K79: carryover from Limo
D80: Sound Quality | E80: Audio and system tones | F80: Play the specified audio at defined volumes. Listen for distortion, speaker buzz and unbalanced sound. Check system tones and identify trim-related noise separately. | G80: 6 | H80: 6 | I80: 6 | K80: carryover from Limo
D81: Harmony & Authenticity | E81: Screen and control consistency | F81: Compare screens and physical controls. Check consistent fonts, icons, colours, wording and feedback for the same action. | G81: 7 | H81: 6 | I81: 6 | K81: carryover from Limo
C82: Interior Lighting | D82: Fit & Finish | E82: Lamp and light-strip fit | F82: Check lamp housings, lenses and light strips. Look for uneven joints, loose parts and misalignment. | G82: 8 | H82: 6 | I82: 8 | K82: DTS/RPS/datum imrpoved | M82: =AVERAGE(G82:G87) -> 7.1666667 | N82: =AVERAGE(H82:H87) -> 5.8333333 | O82: =AVERAGE(I82:I87) -> 6.3333333
D83: Aesthetics | E83: Light colour and uniformity | F83: Switch lights on in a dark cabin. Check bright spots, dark sections, unintended light leakage, colour differences and glare from normal seating positions. | G83: 7 | H83: 6 | I83: 6 | K83: carryover design from Limo/LH
D84: Touch & Feel | E84: Switch feel and scratch resistance | F84: Operate switches and touch accessible housings. Check feedback, rough edges and looseness. Inspect lens and switch scratches after approved use and cleaning tests. | G84: 8 | H84: 6 | I84: 6 | K84: carryover design from Limo/LH
D85: Functionality | E85: Switching and dimming | F85: Test manual switches, door activation, dimming and fitted colour settings. Check correct response, smooth changes and flicker. | G85: 7 | H85: 5 | I85: 6 | K85: carryover design from Limo/LH
D86: Sound Quality | E86: Switch and electrical noise | F86: In a quiet cabin, operate switches and change brightness. Listen for inconsistent clicks or electrical buzzing. Mark N/A where no audible operation applies. | G86: 7 | H86: 6 | I86: 6 | K86: carryover design from Limo/LH
D87: Harmony & Authenticity | E87: Cabin lighting harmony | F87: Compare ambient lights, displays and illuminated controls. Check colour and brightness balance against the approved design. | G87: 6 | H87: 6 | I87: 6 | K87: carryover design from Limo/LH
C88: Interior Hard/Soft trim | D88: Fit & Finish | E88: Trim joints and edge finish | F88: Check pillars, headliner, carpets, sill trims and load-space trim. Look for open joints, lifted edges, exposed clips and incomplete coverage. | G88: 6 | H88: 6 | I88: 8 | K88: carryover design | M88: =AVERAGE(G88:G93) -> 6 | N88: =AVERAGE(H88:H93) -> 6 | O88: =AVERAGE(I88:I93) -> 6.6666667
D89: Aesthetics | E89: Trim surface appearance | F89: Check colour, texture and fabric direction. Look for moulding marks, wrinkles, stains, frayed edges and adhesive traces, including areas exposed during normal use. | G89: 6 | H89: 6 | I89: 7 | K89: carryover design
D90: Touch & Feel | E90: Trim feel and surface damage | F90: Touch normal contact areas. Check rough seams, padding and looseness. Inspect hard-trim scratches after approved use and cleaning tests. Review fabric wear and snagging results separately. | G90: 6 | H90: 6 | I90: 6 | K90: carryover design
D91: Functionality | E91: Movable trim and access | F91: Operate cargo covers, access lids and removable floor panels. Check reach, movement, retention and interference. Mark operating effort N/A for fixed trim. | G91: 6 | H91: 6 | I91: 7 | K91: carryover design
D92: Sound Quality | E92: Interior-trim noise | F92: Listen during occupant movement and the approved road test with specified cargo. Locate squeaks, buzzing and rattles. Record loading conditions. | G92: 6 | H92: 6 | I92: 6 | K92: carryover design
D93: Harmony & Authenticity | E93: Cabin and load-space finish consistency | F93: Compare neighbouring hard trim, fabrics and carpets. Check colour, texture and material transitions against approved samples. | G93: 6 | H93: 6 | I93: 6 | K93: carryover design
C94: Key & Entry | D94: Fit & Finish | E94: Key housing and cover fit | F94: Check key housing joints, buttons and emergency-key covers. Look for uneven gaps, misalignment and loose parts. | G94: 6 | H94: 6 | I94: 8 | K94: carryover design | M94: =AVERAGE(G94:G99) -> 6 | N94: =AVERAGE(H94:H99) -> 6 | O94: =AVERAGE(I94:I99) -> 6.6666667
D95: Aesthetics | E95: Key surface and graphics | F95: Check the key housing, symbols and indicators. Look for scratches, moulding defects, poor printing and uneven finishes. | G95: 6 | H95: 6 | I95: 7 | K95: carryover design
D96: Touch & Feel | E96: Key feel and scratch resistance | F96: Hold the key and press each button. Check grip, edge comfort and feedback. Inspect scratches and worn markings after approved carrying and cleaning tests. | G96: 6 | H96: 6 | I96: 6 | K96: carryover design
D97: Functionality | E97: Locking, unlocking and access | F97: Test fitted key-button, passive-entry, digital-key and emergency-entry functions using the approved scenarios. Check correct response and clear lock/unlock confirmation. | G97: 6 | H97: 6 | I97: 7 | K97: carryover design
D98: Sound Quality | E98: Entry confirmation sound | F98: Lock and unlock the vehicle. Check that confirmation sounds match the actual state. Listen for abnormal handle or actuator noise. | G98: 6 | H98: 6 | I98: 6 | K98: carryover design
D99: Harmony & Authenticity | E99: Key, app and vehicle feedback | F99: Compare key symbols, app messages and vehicle signals. Check consistent wording and feedback for the same action. | G99: 6 | H99: 6 | I99: 6 | K99: carryover design

Sheet Scoring guide PQ
B1: Subjective Scoring guide line with Kansei lenguage
B2: * Kano category may shift by segment and brand positioning
B3: (e.g., Attractive in LCV, Performance in Premium)
B5: PALS | C5: Kanao | D5: Must/Want | E5: PQ Criteria (Kano) | F5: Innovate (Attractive -> Performance) | G5: Customer Experience | H5: Functionality | I5: Aesthetics | J5: Fit & Finish | K5: Harmony & Authenticity | L5: Sound Quality | M5: Touch & Feel
B6: Uncompetitive | C6: Unacceptable / Below competitive | D6: Must Fix | E6: 1 | F6: Unoriginal / Outdated / Boring | G6: Unacceptable; basic expectations are not met | H6: The assessed task cannot be completed. | I6: The overall appearance is seriously damaged by obvious defects. | J6: Parts are visibly misassembled, displaced or poorly seated. | K6: Parts strongly conflict in design, material or finish. | L6: Severe unwanted noise dominates the experience. | M6: Normal contact is very uncomfortable; surfaces or edges are poorly finished.
E7: 2 | F7: Superficial / Cosmetic / Directionless | G7: Major problems; correction is clearly needed | H7: The task frequently fails or requires repeated attempts. | I7: Several major defects are obvious at first viewing. | J7: Large unintended gaps or steps appear at several visible joints. | K7: Several prominent parts look mismatched or poorly integrated. | L7: Loud rattles, harsh impacts or distortion occur repeatedly. | M7: Rough edges, unstable contact areas or severe texture inconsistency are obvious.
E8: 3 | F8: Generic / Me-too / Forgettable | G8: Clearly below expectations; problems affect normal use | H8: The task works, but repeated awkward actions or high effort are needed. | I8: Obvious defects or uneven finishes reduce the overall appearance. | J8: Uneven gaps, steps or alignment errors are easily noticed. | K8: Colour, material or detail differences make the assembly look disconnected. | L8: Unwanted noise is clearly noticeable during normal operation. | M8: Contact areas feel flimsy, uneven or poorly finished.
E9: 4 | F9: Safe / Conservative / Unexciting | G9: Usable, but noticeable problems reduce perceived quality | H9: The task can be completed, but awkward reach, effort or delays are noticeable. | I9: Visible finish variation or weak detailing makes the product look unrefined. | J9: Visible joint variation reduces the impression of assembly quality. | K9: Some prominent details do not match the surrounding design. | L9: Hollow sounds, squeaks or tonal noise reduce perceived quality. | M9: Local roughness, hard seams or unwanted movement reduce comfort.
B10: Border | C10: Border | D10: Want Fix | E10: 5 | F10: Familiar / Evolutionary / Modest | G10: Acceptable in some areas; improvement is still noticeable | H10: The task works correctly, but some steps or feedback need improvement. | I10: The overall appearance is acceptable, but minor visible details need improvement. | J10: Joints are mostly aligned, with local imperfections noticeable in normal viewing. | K10: The design mostly works together, with a few noticeable mismatches. | L10: Operating sound is acceptable, but occasional unwanted noise or weak feedback remains. | M10: Contact feels acceptable, but texture, support or control feedback lacks consistency.
B11: Competitive | C11: Must-Be | E11: 6 | F11: Practical / Useful / Mildly fresh | G11: Meets expected quality for the intended segment | H11: The task is clear and reliable, with manageable effort and response time. | I11: Surfaces and details look clean and balanced under normal viewing conditions. | J11: Gaps, steps and alignment are controlled; minor imperfections do not distract. | K11: Colours, materials and details work together as intended. | L11: Sound suits the function; unwanted noise does not distract under defined conditions. | M11: Contact areas are comfortable and stable; texture and control feel suit their purpose.
B12: Among leader | C12: Performance | E12: 7 | F12: Meaningful / Value-adding / Modern | G12: Noticeably refined in normal use | H12: The task is smooth and predictable, with clear feedback and low effort. | I12: Finish and detailing show noticeable care and consistency. | J12: Visible joints are precise and consistent across the assembly. | K12: Material transitions and design details are well integrated. | L12: Operating sound is pleasant and controlled across normal use conditions. | M12: Grip, texture, support and control resistance feel refined and consistent.
E13: 8 | F13: Wow / Futuristic / Impressive | G13: Strong execution with few weaknesses | H13: The task is easy to complete across different users and common use conditions. | I13: Surfaces and details remain well executed across different viewing angles. | J13: Joint quality remains consistent across visible areas and operating positions. | K13: Design, materials and interaction create a strongly unified experience. | L13: Sound remains well controlled across modes, speeds or loads relevant to the component. | M13: Frequently touched areas maintain refined feel across positions and repeated use.
B14: Leader | C14: Attractive | E14: 9 | F14: Segment-leading / Emotional / Inspiring | G14: Outstanding execution compared with relevant benchmarks | H14: The task feels natural, with very few unnecessary actions and excellent feedback. | I14: Exceptional detailing creates a distinctive and well-executed appearance. | J14: Assembly precision and finish are consistently outstanding against relevant benchmarks. | K14: Material choices and details clearly express the intended design identity. | L14: Feedback and operating sound are exceptionally well matched to the product. | M14: Contact quality and feedback are exceptionally consistent and satisfying.
E15: 10 | F15: Visionary / Radical / Icon-making | G15: Reference-level execution within the evaluated scope | H15: The task delivers an outstanding experience with no meaningful weakness found in the defined evaluation. | I15: Appearance is exceptionally resolved, with no meaningful weakness found under defined viewing conditions. | J15: Joints and finishes provide reference-level execution throughout the evaluated areas. | K15: Design, materials and interaction are fully coherent throughout the evaluated scope. | L15: Sound provides reference-level execution for the intended function and use conditions. | M15: Contact surfaces and controls provide reference-level comfort, stability and feedback.

Sheet A&U Audit Check list
C1: A&U Gate Check List | H1: BM1 | I1: BM2 | J1: BM3
C2: Module | D2: Sub Module | E2: A&U Criteria | F2: Check Item | G2: Evaluation Guide | H2: score | I2: Sore | J2: Score | K2: BM1 comment | L2: BM2 comment | M2: JIRA | N2: BM Row Average | O2: VF6 Row Average | P2: VF6NP Row Average
C3: Exterior | D3: Doors & Closures — Door / Sliding Door | E3: Accessibility / Reach | F3: Handle reach and entry/exit | G3: Ask target users to reach the handle and enter/exit. Record difficult reach, repeated attempts and assistance needed. | H3: 6 | I3: 5 | J3: 5 | L3: Carryover design/paint quality | N3: =AVERAGE(H3:H9) -> 5.8571429 | O3: =AVERAGE(I3:I9) -> 5.5714286 | P3: =AVERAGE(J3:J9) -> 5.5714286
C4: Exterior | D4: Doors & Closures — Door / Sliding Door | E4: Posture | F4: Entry/exit posture | G4: Observe entry and exit. Record head ducking, body twisting, high leg lifting and contact with surrounding parts. | H4: 5 | I4: 5 | J4: 5 | L4: Carryover design/ No special customer delite features/ balanced
C5: Exterior | D5: Doors & Closures — Door / Sliding Door | E5: Comfort | F5: Door operating effort | G5: Open and close the door using the specified method. Record grip discomfort, excessive effort and difficulty controlling movement. | H5: 6 | I5: 6 | J5: 6 | L5: Balanced / Clean / Calm
C6: Exterior | D6: Doors & Closures — Door / Sliding Door | E6: Space Efficiency | F6: Entry/exit clearance | G6: Repeat entry and exit at the specified door opening and parking clearance. Record restricted movement and head, shoulder, knee or foot contact. | H6: 6 | I6: 5 | J6: 5 | L6: Acceptable / Basic / Lacking refinement
C7: Exterior | D7: Doors & Closures — Door / Sliding Door | E7: Convenience / Usability | F7: Daily door-use scenarios | G7: Complete the specified entry and exit tasks, including carrying items where applicable. Record extra steps, failed tasks and assistance needed. | H7: 6 | I7: 6 | J7: 6 | L7: intuitive / Low friction
C8: Exterior | D8: Doors & Closures — Door / Sliding Door | E8: Intuitiveness | F8: Opening, closing and locking logic | G8: Ask a first-time user to open, close, lock and unlock the door without coaching. Record wrong actions and unclear state feedback. | H8: 6 | I8: 6 | J8: 6 | L8: Clean / Clear / Moderate richness / Controlled
C9: Exterior | D9: Doors & Closures — Door / Sliding Door | E9: Visibility | F9: Handle, opening and step visibility | G9: Check in the specified day and night conditions. Record handles, door edges, steps or nearby obstacles that are difficult to see. | H9: 6 | I9: 6 | J9: 6 | L9: Harmonized / Genuine-leaning / Mostly coherent
C10: Exterior | D10: Doors & Closures — Hood | E10: Accessibility / Reach | F10: Release, latch and service-point reach | G10: Operate the release and secondary latch, then reach the specified maintenance points. Record difficult reach and assistance needed. | H10: 5 | I10: 5 | J10: 5 | L10: Carryover door design | N10: =AVERAGE(H10:H16) -> 6.1428571 | O10: =AVERAGE(I10:I16) -> 5.7142857 | P10: =AVERAGE(J10:J16) -> 6
C11: Exterior | D11: Doors & Closures — Hood | E11: Posture | F11: Hood opening and maintenance posture | G11: Open the hood and perform specified maintenance tasks. Record deep bending, extended reach, twisting and difficult working positions. | H11: 7 | I11: 7 | J11: 7 | L11: New design Door handle semi flush
C12: Exterior | D12: Doors & Closures — Hood | E12: Comfort | F12: Hood effort and movement control | G12: Release, lift, support and close the hood using the prescribed method. Record hand discomfort, excessive effort and difficult movement control. | H12: 7 | I12: 6 | J12: 7 | L12: Door handle new design
C13: Exterior | D13: Doors & Closures — Hood | E13: Space Efficiency | F13: Maintenance hand and tool clearance | G13: Perform specified maintenance tasks with the approved tools or containers. Record hand restriction, tool interference and inaccessible working space. | H13: 6 | I13: 5 | J13: 5 | L13: Door handle new design/ poor door closing
C14: Exterior | D14: Doors & Closures — Hood | E14: Convenience / Usability | F14: Owner-maintenance usability | G14: Follow the owner instructions for specified checks and fluid filling. Record extra steps, difficult access and assistance needed. | H14: 6 | I14: 6 | J14: 7 | L14: VF6 legacy mud inturusion improved
C15: Exterior | D15: Doors & Closures — Hood | E15: Intuitiveness | F15: Release, support and closing sequence | G15: Ask a first-time user to open, support and close the hood using available instructions. Record confusion and unclear latch confirmation. | H15: 6 | I15: 5 | J15: 5 | L15: carryover door design/Poor door closing sound
C16: Exterior | D16: Doors & Closures — Hood | E16: Visibility | F16: Latch, labels and service-point visibility | G16: Check the latch, support position, fluid caps and labels under specified lighting. Record items that are difficult to see or identify. | H16: 6 | I16: 6 | J16: 6 | L16: Harmonized / Genuine-leaning / Mostly coherent
C17: Exterior | D17: Doors & Closures — Tailgate | E17: Accessibility / Reach | F17: Handle, closing control and cargo reach | G17: Ask target users to open and close the tailgate and reach designated cargo locations. Record difficult reach and assistance needed. | H17: 6 | I17: 5 | J17: 7 | L17: New design. DTS improved | N17: =AVERAGE(H17:H23) -> 6 | O17: =AVERAGE(I17:I23) -> 5.8571429 | P17: =AVERAGE(J17:J23) -> 6.4285714
C18: Exterior | D18: Doors & Closures — Tailgate | E18: Posture | F18: Loading and unloading posture | G18: Load and retrieve specified items. Record deep bending, twisting, extended reach and awkward lifting. | H18: 6 | I18: 6 | J18: 6 | L18: No special customer delite features/ balanced
C19: Exterior | D19: Doors & Closures — Tailgate | E19: Comfort | F19: Tailgate effort and movement control | G19: Open and close the tailgate using the specified method. Record grip discomfort, excessive effort and difficulty controlling movement. | H19: 6 | I19: 6 | J19: 7 | L19: New design.
C20: Exterior | D20: Doors & Closures — Tailgate | E20: Space Efficiency | F20: Cargo opening and tailgate clearance | G20: Load specified cargo and check the open tailgate against defined parking and overhead clearances. Record contact, required tilting and restricted access. | H20: 6 | I20: 6 | J20: 6 | L20: solid design. RPS/Datum implemented/No ahrp edge
C21: Exterior | D21: Doors & Closures — Tailgate | E21: Convenience / Usability | F21: Daily cargo-access scenarios | G21: Complete specified shopping, luggage and family-use tasks. Record extra steps, blocked access and difficulty opening or closing with occupied hands. | H21: 6 | I21: 6 | J21: 6 | L21: New design LED/projection lamp
C22: Exterior | D22: Doors & Closures — Tailgate | E22: Intuitiveness | F22: Manual/powered tailgate logic | G22: Ask a first-time user to open, stop and close the fitted tailgate. Record wrong button selections and unclear movement or state feedback. | H22: 6 | I22: 6 | J22: 6 | L22: solid design. RPS/Datum implemented
C23: Exterior | D23: Doors & Closures — Tailgate | E23: Visibility | F23: Tailgate and loading-zone visibility | G23: Check the handle, closing controls, tailgate edge and loading area in day and night conditions. Record difficult-to-see areas. | H23: 6 | I23: 6 | J23: 7 | L23: new design improved harmony with surounding part
C24: Exterior | D24: Charging System — Charging Lid / Port | E24: Accessibility / Reach | F24: Lid, port and connector reach | G24: Use the specified parking position and connector. Reach the lid, port and release controls. Record difficult access and assistance needed. | H24: 6 | I24: 5 | J24: 5 | L24: Carryover design/ poor trim fitmenent | N24: =AVERAGE(H24:H30) -> 5.5714286 | O24: =AVERAGE(I24:I30) -> 5.5714286 | P24: =AVERAGE(J24:J30) -> 5.5714286
C25: Exterior | D25: Charging System — Charging Lid / Port | E25: Posture | F25: Connection and disconnection posture | G25: Connect and disconnect the cable. Record bending, twisting, extended reach and difficulty maintaining the working position. | H25: 5 | I25: 5 | J25: 5 | L25: Carryover design
C26: Exterior | D26: Charging System — Charging Lid / Port | E26: Comfort | F26: Connector and cable handling | G26: Handle the specified connector and cable. Record grip discomfort, insertion/removal effort and difficulty supporting the cable. | H26: 5 | I26: 5 | J26: 5 | L26: Carryover design/ exposed wisher line
C27: Exterior | D27: Charging System — Charging Lid / Port | E27: Space Efficiency | F27: Hand and cable clearance | G27: Connect the cable in the specified parking space. Record hand restriction, lid interference and cable-routing conflicts. | H27: 6 | I27: 6 | J27: 6 | L27: Carryover design
C28: Exterior | D28: Charging System — Charging Lid / Port | E28: Convenience / Usability | F28: Daily charging scenarios | G28: Complete approved home and public-charging scenarios under specified lighting and weather conditions. Record failed steps, repeated attempts and assistance needed. | H28: 5 | I28: 6 | J28: 6 | L28: Carryover design/ unclean area remained
C29: Exterior | D29: Charging System — Charging Lid / Port | E29: Intuitiveness | F29: Charging sequence and status | G29: Ask a first-time user to start and stop charging without coaching. Record wrong actions and uncertainty about connection, charging or release status. | H29: 6 | I29: 6 | J29: 6 | L29: Carryover design
C30: Exterior | D30: Charging System — Charging Lid / Port | E30: Visibility | F30: Port orientation and status visibility | G30: Check the port, connector orientation and status indicators in daylight and darkness. Record information that is difficult to see or distinguish. | H30: 6 | I30: 6 | J30: 6 | L30: Carryover design
C31: Exterior | D31: Exterior Trim — Side Step | E31: Accessibility / Reach | F31: Step-assisted entry/exit | G31: Ask target users to enter and exit using the step. Record difficulty reaching the step or supporting handhold and assistance needed. | H31: 6 | I31: 5 | J31: 7 | L31: new design improved DTS/RPS/Location strategy | N31: =AVERAGE(H31:H37) -> 6 | O31: =AVERAGE(I31:I37) -> 5.5714286 | P31: =AVERAGE(J31:J37) -> 6.2857143
C32: Exterior | D32: Exterior Trim — Side Step | E32: Posture | F32: Step-assisted body movement | G32: Observe step use during entry and exit. Record excessive leg lifting, twisting, awkward foot placement and body contact. | H32: 6 | I32: 6 | J32: 6 | L32: No special customer delite features/ balanced
C33: Exterior | D33: Exterior Trim — Side Step | E33: Comfort | F33: Foot support and confidence | G33: Use approved footwear and surface conditions. Record pressure discomfort, unstable footing and perceived slipping. Refer slip concerns for specialist assessment. | H33: 6 | I33: 6 | J33: 7 | L33: new design improved DTS
C34: Exterior | D34: Exterior Trim — Side Step | E34: Space Efficiency | F34: Usable foothold and clearance | G34: Check foot placement and body clearance for target users. Record insufficient foothold, door interference and restriction of the entry path. | H34: 6 | I34: 5 | J34: 6 | L34: Mostly solid/ no sharp edges on A surface
C35: Exterior | D35: Exterior Trim — Side Step | E35: Convenience / Usability | F35: Daily access assistance | G35: Complete specified entry/exit tasks with carried items where applicable. Record whether the step helps access or creates extra movements and clothing contact. | H35: 6 | I35: 6 | J35: 6 | L35: Reliable
C36: Exterior | D36: Exterior Trim — Side Step | E36: Intuitiveness | F36: Step-use recognition | G36: Ask a first-time user to enter without coaching. Record uncertainty about where to step or where to hold. | H36: 6 | I36: 5 | J36: 6 | L36: solid design. RPS/Datum implemented
C37: Exterior | D37: Exterior Trim — Side Step | E37: Visibility | F37: Step surface and edge visibility | G37: Check from approach and exit positions in day and night conditions. Record step surfaces or edges that are difficult to see. | H37: 6 | I37: 6 | J37: 6 | L37: well integrated panel matching with trim
C38: Exterior | D38: Mirror System — ORVM | E38: Accessibility / Reach | F38: Mirror-control reach | G38: From the specified driving position, operate mirror controls. Record difficult reach and the need to leave the normal seated position. | H38: 6 | I38: 6 | J38: 6 | L38: new design improved DTS | N38: =AVERAGE(H38:H44) -> 6 | O38: =AVERAGE(I38:I44) -> 6 | P38: =AVERAGE(J38:J44) -> 6.2857143
C39: Exterior | D39: Mirror System — ORVM | E39: Posture | F39: Mirror-viewing posture | G39: Adjust mirrors and view specified targets. Record excessive head movement, neck rotation and body leaning. | H39: 6 | I39: 6 | J39: 6 | L39: No special customer delite features/ balanced
C40: Exterior | D40: Mirror System — ORVM | E40: Comfort | F40: Mirror-view comfort | G40: View specified targets under approved conditions. Record eye strain, distracting reflections, image vibration and perceived distortion. | H40: 6 | I40: 6 | J40: 7 | L40: new design improved DTS
C41: Exterior | D41: Mirror System — ORVM | E41: Space Efficiency | F41: Mirror adjustment and movement clearance | G41: Operate fitted adjustment and folding functions. Record interference with adjacent parts or restrictions in the required movement range. | H41: 6 | I41: 6 | J41: 6 | L41: Mostly solid/ no sharp edges on A surface
C42: Exterior | D42: Mirror System — ORVM | E42: Convenience / Usability | F42: Daily mirror functions | G42: Complete specified adjustment, folding, heating and memory tasks where fitted. Record extra steps, delays and unclear function status. | H42: 6 | I42: 6 | J42: 6 | L42: Reliable
C43: Exterior | D43: Mirror System — ORVM | E43: Intuitiveness | F43: Mirror-control logic | G43: Ask a first-time user to select, adjust and fold the mirrors. Record wrong selections and unclear control or status feedback. | H43: 6 | I43: 6 | J43: 6 | L43: solid design. RPS/Datum implemented
C44: Exterior | D44: Mirror System — ORVM | E44: Visibility | F44: Side/rear targets and obstruction | G44: From specified seating positions, check defined side and rear targets. Record blocked views and extra movement needed to see them. | H44: 6 | I44: 6 | J44: 7 | L44: well integrated wheel design with exterior
C45: Exterior | D45: Exterior Lighting System | E45: Accessibility / Reach | F45: Lighting-control reach | G45: From the specified driving position, reach and operate lighting controls. Record difficult reach and controls that require body movement. | H45: 7 | I45: 5 | J45: 8 | L45: new design. DTS/RPS/datum imrpoved | N45: =AVERAGE(H45:H51) -> 7 | O45: =AVERAGE(I45:I51) -> 5.5714286 | P45: =AVERAGE(J45:J51) -> 7.8571429
C46: Exterior | D46: Exterior Lighting System | E46: Posture | F46: Lighting-control posture | G46: Operate specified lighting functions while stationary or in an approved simulator. Record leaning, stretching and loss of normal seated posture. | H46: 7 | I46: 6 | J46: 7 | L46: No special customer delite features/ balanced
C47: Exterior | D47: Exterior Lighting System | E47: Comfort | F47: Driver visual comfort | G47: In the approved night evaluation, check reflections and bright areas visible to the driver. Record glare discomfort and difficulty viewing required targets. | H47: 7 | I47: 5 | J47: 8 | L47: new design
C48: Exterior | D48: Exterior Lighting System | E48: Space Efficiency | F48: Control-operation clearance | G48: Check hand clearance around physical lighting controls, if fitted. Record interference or accidental contact with adjacent controls. Mark N/A if no applicable clearance check exists. | H48: 8 | I48: 6 | J48: 8 | L48: soft touch IP top cover with chrome finisher
C49: Exterior | D49: Exterior Lighting System | E49: Convenience / Usability | F49: Lighting-use scenarios | G49: Complete approved night, parking, approach and adverse-weather scenarios. Record difficult selection, extra steps and unclear operating status. | H49: 7 | I49: 5 | J49: 8 | L49: Glove box volume increase.
C50: Exterior | D50: Exterior Lighting System | E50: Intuitiveness | F50: Lighting modes and feedback | G50: Ask a first-time user to select applicable lighting modes. Record incorrect selections and uncertainty about active modes or automatic operation. | H50: 6 | I50: 6 | J50: 8 | L50: soft touch IP top cover
C51: Exterior | D51: Exterior Lighting System | E51: Visibility | F51: Illuminated targets and signal recognition | G51: Check specified road, approach and signal targets under approved conditions. Record difficult-to-see targets and indicators. Refer performance concerns to Lighting Engineering. | H51: 7 | I51: 6 | J51: 8 | L51: Good integration with IP vs Door trim
C52: Interior | D52: Instrument Panel | E52: Accessibility / Reach | F52: IP-control reach | G52: From specified seating positions, reach key controls, vents and displays. Record difficult reach and inaccessible controls. | H52: 7 | I52: 7 | J52: 8 | L52: New design Carry over from VF7NP | N52: =AVERAGE(H52:H58) -> 6.8571429 | O52: =AVERAGE(I52:I58) -> 6.4285714 | P52: =AVERAGE(J52:J58) -> 7.1428571
C53: Interior | D53: Instrument Panel | E53: Posture | F53: IP-operation posture | G53: Operate specified controls. Record leaning, twisting, shoulder lifting and loss of back support. | H53: 6 | I53: 6 | J53: 6 | L53: No special customer delite features/ balanced / competitive with BYD dolphin
C54: Interior | D54: Instrument Panel | E54: Comfort | F54: Repeated-control-use comfort | G54: Repeat specified control tasks. Record hand or arm discomfort, visual discomfort and perceived mental effort. | H54: 7 | I54: 7 | J54: 7 | L54: New design/ competitive with BYD dolphin
C55: Interior | D55: Instrument Panel | E55: Space Efficiency | F55: Hand clearance and layout spacing | G55: Check hand clearance around controls and vents. Record interference, cramped operation and unintended contact with neighbouring parts. | H55: 7 | I55: 7 | J55: 7 | L55: new CMF/ leather cover/ improved size
C56: Interior | D56: Instrument Panel | E56: Convenience / Usability | F56: Daily driver-control tasks | G56: Complete specified driver-control tasks while stationary or in an approved simulator. Record extra steps, errors and assistance needed. | H56: 7 | I56: 6 | J56: 8 | L56: Adding wheel control switch packs/ steering wheel stalks
C57: Interior | D57: Instrument Panel | E57: Intuitiveness | F57: Control grouping and information logic | G57: Ask a first-time user to find and operate specified functions. Record searching, wrong selections and unclear information. | H57: 6 | I57: 6 | J57: 6 | L57: New design
C58: Interior | D58: Instrument Panel | E58: Visibility | F58: Displays, warnings and control visibility | G58: Check cluster, displays and controls from specified eye positions in day and night conditions. Record blocked information, reflections and unreadable symbols. | H58: 8 | I58: 6 | J58: 8 | L58: New design harmony with interior design
C59: Interior | D59: Steering Wheel System | E59: Accessibility / Reach | F59: Button and control reach | G59: From the specified driving posture, operate each control. Record thumb stretching, grip changes and inaccessible controls. | H59: 7 | I59: 5 | J59: 8 | L59: new design. DTS/RPS/datum imrpoved | N59: =AVERAGE(H59:H65) -> 6.8571429 | O59: =AVERAGE(I59:I65) -> 5.2857143 | P59: =AVERAGE(J59:J65) -> 7.4285714
C60: Interior | D60: Steering Wheel System | E60: Posture | F60: Grip and arm posture | G60: Hold the wheel at specified grip positions. Record bent wrists, raised shoulders, overextended arms and loss of back support. | H60: 6 | I60: 5 | J60: 7 | L60: wireless charger/ USP C
C61: Interior | D61: Steering Wheel System | E61: Comfort | F61: Grip and button comfort | G61: Hold the wheel and repeat specified button operations. Record pressure points, seam discomfort, grip fatigue and excessive button effort. | H61: 7 | I61: 6 | J61: 8 | L61: new design
C62: Interior | D62: Steering Wheel System | E62: Space Efficiency | F62: Hand and body clearance | G62: Check specified seat and wheel positions. Record hand or knee interference and restricted operating space. | H62: 7 | I62: 5 | J62: 7 | L62: Arm rest soft cover
C63: Interior | D63: Steering Wheel System | E63: Convenience / Usability | F63: Steering-control tasks | G63: Complete specified control tasks while stationary or in an approved simulator. Record errors, accidental activation and unnecessary grip changes. | H63: 8 | I63: 5 | J63: 8 | L63: wirless charger/ more storage space/cup holders
C64: Interior | D64: Steering Wheel System | E64: Intuitiveness | F64: Button meaning and grouping | G64: Ask a first-time user to identify and operate specified functions. Record misunderstood symbols, wrong buttons and unclear feedback. | H64: 6 | I64: 5 | J64: 6 | L64: solid design. RPS/Datum implemented
C65: Interior | D65: Steering Wheel System | E65: Visibility | F65: Buttons and cluster visibility | G65: Check button symbols and cluster information across specified seat and wheel positions. Record blocked or difficult-to-read information. | H65: 7 | I65: 6 | J65: 8 | L65: New design harmony with interior design
C66: Interior | D66: Center Console | E66: Accessibility / Reach | F66: Console-feature reach | G66: From specified seating positions, reach storage, cupholders, charging areas and controls. Record difficult reach and inaccessible features. | H66: 7 | I66: 5 | J66: 8 | L66: new design. DTS/RPS/datum imrpoved | N66: =AVERAGE(H66:H72) -> 7.1428571 | O66: =AVERAGE(I66:I72) -> 5.5714286 | P66: =AVERAGE(J66:J72) -> 7.4285714
C67: Interior | D67: Center Console | E67: Posture | F67: Console-operation posture | G67: Use specified console features. Record twisting, leaning, shoulder strain and awkward arm movement. | H67: 7 | I67: 6 | J67: 7 | L67: No special customer delite features/ balanced
C68: Interior | D68: Center Console | E68: Comfort | F68: Arm support and contact comfort | G68: Use the armrest and console features for the specified duration. Record pressure points, unsupported arms and uncomfortable contact. | H68: 8 | I68: 6 | J68: 8 | L68: new design Harmonious / Stylish / Confident
C69: Interior | D69: Center Console | E69: Space Efficiency | F69: Item fit and operating clearance | G69: Place specified cups, phones and items in the console. Record poor fit, hand restriction and interference between features. | H69: 7 | I69: 6 | J69: 7 | L69: Arm rest soft cover
C70: Interior | D70: Center Console | E70: Convenience / Usability | F70: Daily console tasks | G70: Store and retrieve specified items and use fitted charging functions. Record extra steps, difficult removal and restrictions during simultaneous use. | H70: 7 | I70: 5 | J70: 8 | L70: Door pull cup design/easy access of switchs
C71: Interior | D71: Center Console | E71: Intuitiveness | F71: Console layout and controls | G71: Ask a first-time user to locate and use specified features. Record unclear openings, controls, item orientation and status feedback. | H71: 6 | I71: 5 | J71: 6 | L71: solid design. RPS/Datum implemented
C72: Interior | D72: Center Console | E72: Visibility | F72: Console controls and stored items | G72: Check controls, openings and charging indicators in day and night conditions. Record hidden items, unreadable symbols and difficult-to-see status. | H72: 8 | I72: 6 | J72: 8 | L72: New design harmony with interior design
C73: Interior | D73: Door Trim | E73: Accessibility / Reach | F73: Handle, switch and pocket reach | G73: From specified seating positions, reach handles, switches and pockets. Record difficult reach and inaccessible features. | H73: 7 | I73: 6 | J73: 8 | L73: New design. DTS/RPS/datum imrpoved | N73: =AVERAGE(H73:H79) -> 7.1428571 | O73: =AVERAGE(I73:I79) -> 6 | P73: =AVERAGE(J73:J79) -> 7.2857143
C74: Interior | D74: Door Trim | E74: Posture | F74: Armrest and switch-use posture | G74: Rest the arm and operate switches. Record raised shoulders, bent wrists and awkward elbow or body positions. | H74: 6 | I74: 6 | J74: 6 | L74: No special customer delite features/ balanced
C75: Interior | D75: Door Trim | E75: Comfort | F75: Arm and hand-contact comfort | G75: Use the armrest, handle and switches for the specified duration. Record pressure points, hard-edge contact and operating discomfort. | H75: 8 | I75: 6 | J75: 8 | L75: new design Harmonious / Stylish / Confident
C76: Interior | D76: Door Trim | E76: Space Efficiency | F76: Pocket capacity and arm clearance | G76: Use specified pocket items and arm positions. Record poor fit, restricted hand clearance and interference with occupants or controls. | H76: 8 | I76: 7 | J76: 7 | L76: leather PU cover/ fabric
C77: Interior | D77: Door Trim | E77: Convenience / Usability | F77: Door-trim use scenarios | G77: Complete specified release, locking, window and storage tasks. Record extra steps, accidental activation and difficult item retrieval. | H77: 7 | I77: 5 | J77: 8 | L77: Rear Seat thigh support imroved/ seat back reclining angle imroved
C78: Interior | D78: Door Trim | E78: Intuitiveness | F78: Switch grouping and operation logic | G78: Ask a first-time user to operate specified switches and releases. Record wrong selections, unclear symbols and confusing operation. | H78: 6 | I78: 6 | J78: 6 | L78: solid design. RPS/Datum implemented
C79: Interior | D79: Door Trim | E79: Visibility | F79: Handle, switch and indicator visibility | G79: Check handles, switch symbols, pockets and lock indicators in day and night conditions. Record difficult-to-see features. | H79: 8 | I79: 6 | J79: 8 | L79: New design harmony with interior design
C80: Interior | D80: HVAC System | E80: Accessibility / Reach | F80: HVAC-control and vent reach | G80: From specified seating positions, reach HVAC controls and vent adjusters. Record difficult reach and inaccessible controls. | H80: 7 | I80: 6 | J80: 8 | L80: New design. DTS/RPS/datum imrpoved | N80: =AVERAGE(H80:H86) -> 7 | O80: =AVERAGE(I80:I86) -> 5.8571429 | P80: =AVERAGE(J80:J86) -> 7.2857143
C81: Interior | D81: HVAC System | E81: Posture | F81: HVAC-operation posture | G81: Adjust temperature, mode and vent direction. Record leaning, stretching and awkward hand or arm positions. | H81: 6 | I81: 6 | J81: 6 | L81: No special customer delite features/ balanced
C82: Interior | D82: HVAC System | E82: Comfort | F82: Thermal and airflow comfort | G82: Use specified climate settings and conditions. Record hot/cold discomfort, unwanted drafts and uneven comfort across occupied seats. | H82: 7 | I82: 6 | J82: 8 | L82: new design Harmonious / Stylish / Confident
C83: Interior | D83: HVAC System | E83: Space Efficiency | F83: Vent and control-operation clearance | G83: Operate vent adjusters and physical controls where fitted. Record restricted hand space, interference and limited usable adjustment. | H83: 7 | I83: 5 | J83: 7 | L83: Carry over air vent design from VF7NP
C84: Interior | D84: HVAC System | E84: Convenience / Usability | F84: Daily climate tasks | G84: Complete specified cooling, heating and demisting tasks. Record extra steps, errors and difficulty achieving the requested setting. | H84: 7 | I84: 6 | J84: 7 | L84: Carry over air vent design from VF7NP
C85: Interior | D85: HVAC System | E85: Intuitiveness | F85: Climate-control logic | G85: Ask a first-time user to set temperature, fan, mode and applicable automatic functions. Record misunderstood icons and unclear active states. | H85: 7 | I85: 6 | J85: 7 | L85: Carry over air vent design from VF7NP
C86: Interior | D86: HVAC System | E86: Visibility | F86: HVAC information and status | G86: Check settings, icons and active-state indications in day and night conditions. Record unreadable or ambiguous information. | H86: 8 | I86: 6 | J86: 8 | L86: new design/ harmony with IP interior with chrome finish
C87: Interior | D87: Infotainment System | E87: Accessibility / Reach | F87: Screen and control reach | G87: From specified seating positions, reach required screen areas and physical controls. Record difficult reach and inaccessible touch targets. | H87: 8 | I87: 6 | J87: 8 | L87: DTS/RPS/datum imrpoved | N87: =AVERAGE(H87:H93) -> 7 | O87: =AVERAGE(I87:I93) -> 6 | P87: =AVERAGE(J87:J93) -> 6.4285714
C88: Interior | D88: Infotainment System | E88: Posture | F88: Touchscreen-operation posture | G88: Perform specified screen tasks. Record extended reach, body leaning, shoulder lifting and unsupported arm positions. | H88: 8 | I88: 7 | J88: 7 | L88: No special customer delite features/ balanced
C89: Interior | D89: Infotainment System | E89: Comfort | F89: Visual and mental comfort | G89: Complete specified tasks under approved conditions. Record eye strain, perceived mental effort and difficulty maintaining attention. | H89: 7 | I89: 6 | J89: 6 | L89: carryover from Limo
C90: Interior | D90: Infotainment System | E90: Space Efficiency | F90: Touch-target spacing and hand clearance | G90: Check frequently used touch targets and surrounding hand space. Record cramped selection, unintended adjacent presses and physical interference. | H90: 6 | I90: 6 | J90: 6 | L90: carryover from Limo
C91: Interior | D91: Infotainment System | E91: Convenience / Usability | F91: Navigation, media and phone tasks | G91: Complete approved navigation, media, phone and settings tasks. Record failed steps, delays and recovery difficulties. Record the software version. | H91: 7 | I91: 5 | J91: 6 | L91: carryover from Limo
C92: Interior | D92: Infotainment System | E92: Intuitiveness | F92: Menu structure and feedback | G92: Ask a first-time user to complete specified tasks without coaching. Record wrong selections, backtracking and unclear feedback. | H92: 6 | I92: 6 | J92: 6 | L92: carryover from Limo
C93: Interior | D93: Infotainment System | E93: Visibility | F93: Screen readability and reflections | G93: Check screen content in day, night and specified sunlight conditions. Record reflections, unreadable content and poor symbol contrast. | H93: 7 | I93: 6 | J93: 6 | L93: carryover from Limo
C94: Interior | D94: Interior Lighting | E94: Accessibility / Reach | F94: Lighting-control reach | G94: From relevant seats and access positions, reach fitted lighting controls. Record difficult reach and inaccessible controls. | H94: 8 | I94: 6 | J94: 8 | L94: DTS/RPS/datum imrpoved | N94: =AVERAGE(H94:H100) -> 7 | O94: =AVERAGE(I94:I100) -> 5.8571429 | P94: =AVERAGE(J94:J100) -> 6.2857143
C95: Interior | D95: Interior Lighting | E95: Posture | F95: Lighting-operation posture | G95: Operate lights during specified seating, reading and storage tasks. Record stretching, twisting and awkward arm positions. | H95: 6 | I95: 6 | J95: 6 | L95: No special customer delite features/ balanced
C96: Interior | D96: Interior Lighting | E96: Comfort | F96: Brightness and glare comfort | G96: From specified seating positions, use the lighting settings. Record direct glare, distracting reflections and brightness discomfort. | H96: 7 | I96: 6 | J96: 6 | L96: carryover design from Limo/LH
C97: Interior | D97: Interior Lighting | E97: Space Efficiency | F97: Lighting-control clearance | G97: Check hand clearance around physical lighting controls, if fitted. Record interference with adjacent parts. Mark N/A where no applicable clearance check exists. | H97: 8 | I97: 6 | J97: 6 | L97: carryover design from Limo/LH
C98: Interior | D98: Interior Lighting | E98: Convenience / Usability | F98: Night-use tasks | G98: Complete specified entry, reading, item-search and loading tasks in darkness. Record extra actions and tasks made difficult by the lighting. | H98: 7 | I98: 5 | J98: 6 | L98: carryover design from Limo/LH
C99: Interior | D99: Interior Lighting | E99: Intuitiveness | F99: Lighting-control and automatic logic | G99: Ask a first-time user to switch, dim and select fitted lighting functions. Record wrong actions and confusion about automatic activation or switch-off. | H99: 7 | I99: 6 | J99: 6 | L99: carryover design from Limo/LH
C100: Interior | D100: Interior Lighting | E100: Visibility | F100: Task-area and object visibility | G100: In a dark cabin, read and find specified objects. Record dark areas, shadows and lighting that prevents clear viewing. | H100: 6 | I100: 6 | J100: 6 | L100: carryover design from Limo/LH
...

Sheet Scoring guide A&U
D3: PALS | E3: Kano | F3: Must / Want | G3: Score | H3: Accessibility | I3: Posture | J3: Comfort | K3: Space Efficiency | L3: Convenience & Usability | M3: Intuitiveness | N3: Visibility
D4: Uncompetitive | E4: Unacceptable / Below competitive | F4: Must Fix | G4: 1 | H4: The required feature cannot be reached or accessed by the target user. | I4: The task cannot be completed in a usable posture. | J4: Pain or severe discomfort prevents continued use. | K4: The target occupant or required item cannot be accommodated. | L4: The required task cannot be completed. | M4: The user cannot understand how to complete the task without assistance. | N4: The required object or information cannot be seen from the intended position.
G5: 2 | H5: Access requires assistance or a major change of body position. | I5: Deep bending, strong twisting or extended reach is repeatedly required. | J5: Strong pressure or fatigue requires the user to stop or change position frequently. | K5: Severe space restrictions prevent normal movement or item handling. | L5: The task frequently fails or requires assistance and repeated attempts. | M5: The user repeatedly selects the wrong action and needs substantial guidance. | N5: Major obstruction, glare or poor lighting makes the required target very difficult to see.
G6: 3 | H6: Access requires noticeable stretching, leaning or several attempts. | I6: The task requires an awkward posture that is difficult to maintain. | J6: Clear discomfort develops during the specified use period. | K6: Several contact or interference points restrict normal use. | L6: The task is completed with repeated extra steps, errors or workarounds. | M6: The user completes the task only after repeated trial and error. | N6: The user must repeatedly reposition or search to see the required target.
G7: 4 | H7: Access is possible, but noticeable reach effort or repositioning remains. | I7: Some bending, twisting or loss of support is needed during normal use. | J7: Local pressure or discomfort reduces the quality of normal use. | K7: Local clearance restrictions require repositioning of the body or items. | L7: The task works, but awkward steps or occasional retries are needed. | M7: The user hesitates or makes an incorrect selection before understanding the task. | N7: Some required targets are difficult to see because of obstruction, glare or low contrast.
D8: Border | E8: Border | F8: Want Fix | G8: 5 | H8: Access is acceptable, with minor stretching or repositioning. | I8: The posture is acceptable, but local awkwardness remains. | J8: Comfort is acceptable, but mild discomfort remains over the specified duration. | K8: Occupants and items fit, but usable clearance or retrieval space is limited. | L8: The task is completed reliably, but avoidable steps or inconvenience remain. | M8: The user understands the task after brief searching or a minor correction. | N8: The target can be seen, but some viewing effort or adjustment is needed.
D9: Competitive | E9: Must-Be | G9: 6 | H9: Required features are reached using normal movement for the task. | I9: The task is completed in a natural posture with adequate support. | J9: Comfort meets the approved target over the specified use duration. | K9: Target occupants and items fit with sufficient clearance for normal use. | L9: The task is completed reliably with clear steps and manageable effort. | M9: The user completes the task with little hesitation and clear feedback. | N9: Required targets are clearly visible under the defined evaluation conditions.
D10: Among Leader | E10: Performance | G10: 7 | H10: Access is easy and repeatable, with little need to reposition. | I10: The posture remains natural and supported throughout the task. | J10: Support and contact feel remain comfortable during repeated use. | K10: Space supports easy movement, placement and retrieval of specified items. | L10: The task is smooth and predictable, with few unnecessary actions. | M10: The user quickly identifies the correct action and understands the result. | N10: Targets are easy to identify, with well-controlled glare and obstruction.
G11: 8 | H11: Access remains easy across the defined users and common use scenarios. | I11: Good posture is maintained across the defined users and adjustment positions. | J11: Comfort remains consistent across the defined users and intended conditions. | K11: Space supports the specified uses together with little interference. | L11: The task remains easy across common scenarios, with clear recovery from errors. | M11: Related tasks use consistent logic and require little learning. | N11: Visibility remains clear across the specified positions and lighting conditions.
D12: Leader | E12: Attractive | G12: 9 | H12: Access is exceptionally well resolved against relevant benchmarks. | I12: Posture and support are exceptionally well resolved against relevant benchmarks. | J12: Comfort and support are outstanding over the intended use duration. | K12: Available space is exceptionally usable without compromising neighbouring functions. | L12: The complete use sequence is exceptionally convenient against relevant benchmarks. | M12: First-time use is exceptionally clear, including status and error recovery. | N12: Required targets are exceptionally easy to identify against relevant benchmarks.
G13: 10 | H13: Reference-level access is demonstrated throughout the evaluated scope. | I13: Reference-level posture and support are demonstrated throughout the evaluated scope. | J13: Reference-level comfort is demonstrated for the defined users and duration. | K13: Reference-level space utilization is demonstrated for the specified occupants and tasks. | L13: Reference-level task flow is demonstrated with no meaningful usability weakness found. | M13: Reference-level first-use understanding is demonstrated throughout the evaluated tasks. | N13: Reference-level visibility is demonstrated throughout the defined evaluation conditions.

Sheet Must_Want Fix Guide
B2: ⏹ Issue clarifications (Safety/Functionality/Appearance)
B4: Group | C4: Effect | D4: VF DFMEA Severity | E4: VF JIRA Severity | F4: VCA Mapping | G4: Classification | H4: Customer Effect Criteria | I4: Assessment Checkpoints | J4: Lead Assessment Group / PIC | K4: Supporting Assessment Groups | L4: Must Fix / Want Fix | M4: Deviation Eligibility | N4: Example
B5: Safety / Regulatory | C5: Failure to Meet Safety and/or Regulatory Requirements | D5: 10 | E5: PS / PL | F5: 50 | G5: <CC> Critical Characteristics | H5: Affects safe vehicle operation and/or regulatory compliance without warning | I5: Safety hazard; applicable legal requirement; warning availability and effectiveness | J5: Safety / FuSa / VPAC; Homologation / Compliance for regulatory issues | K5: Relevant System / Component Engineering; EE / Software; Validation / DVP; VCA / Quality; Manufacturing / Supplier Quality; After-sales | L5: Must Fix | M5: Not permitted — correction and verification required | N5: 1. Brakes fail without warning, preventing safe stopping. 2. Steering control is lost without warning. 3. An electrical fault causes a fire without warning.
D6: 9 | H6: Affects safe vehicle operation and/or regulatory compliance with warning | L6: Must Fix | M6: Not permitted — correction and verification required | N6: 1. Brakes fail despite a warning, preventing safe stopping. 2. Steering control is lost despite a warning. 3. An electrical fault causes a fire despite a warning.
B7: Functional | C7: Loss or Degradation of Primary Function | D7: 8 | E7: W | F7: 50 | G7: <SC> Significant Characteristics | H7: Loss of primary function; vehicle inoperable, without affecting safe operation | I7: Vehicle operability; failed driving function; performance against approved requirements | J7: Relevant Function Engineering Team + VCA | K7: Vehicle Architecture; EE / Software / Controls; Validation / Reliability; Manufacturing / QE / QC; Supplier Quality; After-sales; relevant attribute teams | L7: Must Fix | M7: Not permitted — correction and verification required | N7: 1. The parked vehicle cannot enter Ready mode. 2. Drive cannot be selected while parked. 3. The parked vehicle has no drive power.
D8: 7 | H8: Degradation of primary function; vehicle operable with reduced performance | L8: Must Fix | M8: Not permitted — correction and verification required | N8: 1. Drive power is below the required level. 2. Acceleration is below the required performance. 3. Vehicle speed is unexpectedly limited below the required level.
C9: Loss or Degradation of Secondary Function | D9: 6 | E9: A | F9: 40 | G9: <HIC> High Importance Characteristics | H9: Loss of secondary function; vehicle operable, but comfort/convenience function inoperable | I9: Function availability; operating performance; required user effort; daily-use inconvenience | J9: Relevant Function Engineering Team + VCA; A&U for usability and ergonomics | K9: EE / Software / UX; Vehicle Architecture; Validation / Reliability; PQ / GD&T where applicable; Manufacturing / QE / QC; Supplier Quality; After-sales | L9: Must Fix | M9: Not permitted — correction and verification required | N9: 1. The seat heater does not work. 2. The audio system produces no sound. 3. The seat massage function does not work.
D10: 5 | H10: Degradation of secondary function; reduced comfort/convenience performance | L10: Must Fix | M10: Not permitted — correction and verification required | N10: 1. The seat heater takes longer than the required warm-up time. 2. The audio system repeatedly cuts out. 3. Seat massage strength is below the required level.
B11: Appearance / Sound / Perceived Quality | C11: Customer Perception/ Annoyance | D11: 4 | E11: B | F11: 20 | G11: <STD> Standard Characteristics | H11: Appearance or audible-noise nonconformity noticed by most customers >75% | I11: Visibility / audibility under defined conditions; gap / flush consistency; surface defects; colour / grain / gloss harmony; customer acceptance | J11: Relevant Attribute Owner + VCA: PQ / GD&T / A&U / Sound–NVH, according to the issue | K11: Styling / CMF; Body / Interior / Exterior Engineering; EE / UX where applicable; Materials / Paint; Validation / Reliability; Manufacturing / QE / QC; Supplier Quality; After-sales | L11: Must Fix | M11: Not permitted — correction and verification required | N11: 1. Easily visible permanent trim scratches/Sink /gate /paint defects 2. Excessive wind noise fails the highway-driving acceptance criteria. 3. Uneven panel gaps fail the appearance acceptance criteria.
D12: 3 | E12: C | F12: 5 | H12: Appearance or audible-noise nonconformity noticed by many customers >50% | L12: Want Fix | M12: May be approved based on condition | N12: 1. A small trim colour difference is noticeable but acceptable. 2. A minor panel alignment difference is noticeable but acceptable. 3. A slightly hollow switch sound is noticeable but acceptable.
D13: 2 | H13: Appearance or audible-noise nonconformity noticed by discriminating customers >25%, per internal source | L13: Want Fix | M13: May be approved based on condition | N13: 1. A minor trim gloss difference is acceptable. 2. A slight grain difference between trim parts is acceptable. 3. A faint trim squeak under specific conditions is acceptable.
C14: No effect | D14: 1 | E14: No issue / lowest classification | F14: 1 | H14: No discernible effect | I14: Confirm no customer effect and check mandatory requirement | J14: Relevant Attribute / Function Owner | K14: VCA / Quality and other affected groups, as required | L14: No Fix Required | M14: Generally not required | N14: 1. A hidden trim surface has a cosmetic mark with no other effect. 2. A hidden moulding mark has no customer or performance effect. 3. A hidden colour difference has no customer or performance effect.
B16: ⏹ Must fix Permanent Deviation Proposal Eligibility
B17: Permanent Deviation may be proposed by the responsible Engineering organization when one or more of the following conditions exist:
B18: 1. Engineering or technical limitations prevent full compliance within the program timeline.
B19: 2. Manufacturing or process limitations prevent achievement of the target requirement.
B20: 3. The cost required for correction is disproportionate to the customer benefit or business impact.
B21: 4. The implementation timing required for correction is not compatible with the approved program milestone or SOP timing.
B22: 5. Customer impact is assessed as low and acceptable based on cross-functional evaluation.
B23: ⏹ Must fix Permanent Deviation Approval Rules
B24: Permanent Deviation may only be considered when all conditions below are satisfied:
B25: 1. No Safety impact.
B26: 2. No Regulatory / Homologation impact.
B27: 3. No Primary Function impact.
... B32: 8. Approval by the responsible quality authority is obtained.

Sheet Sheet11

Sheet PQ Criteria
B1: PQ Criteria | C1: BYD | D1: VF6 | E1: VF6NP | F1: Competitive Position | G1: Assessment
B2: Functionality | C2: =AVERAGE('PQ Audit Checklist'!G7,'PQ Audit Checklist'!G13,'PQ Audit Checklist'!G19,'PQ Audit Checklist'!G25,'PQ Audit Checklist'!G31,'PQ Audit Checklist'!G37,'PQ Audit Checklist'!G43,'PQ Audit Checklist'!G49,'PQ Audit Checklist'!G55,'PQ Audit Checklist'!G61,'PQ Audit Checklist'!G67,'PQ Audit Checklist'!G73:G79,'PQ Audit Checklist'!G73,'PQ Audit Checklist'!G85,'PQ Audit Checklist'!G97) -> 6.7142857 | D2: =AVERAGE('PQ Audit Checklist'!H7,'PQ Audit Checklist'!H13,'PQ Audit Checklist'!H19,'PQ Audit Checklist'!H25,'PQ Audit Checklist'!H31,'PQ Audit Checklist'!H37,'PQ Audit Checklist'!H43,'PQ Audit Checklist'!H49,'PQ Audit Checklist'!H55,'PQ Audit Checklist'!H61,'PQ Audit Checklist'!H67,'PQ Audit Checklist'!H73:H79,'PQ Audit Checklist'!H73,'PQ Audit Checklist'!H85,'PQ Audit Checklist'!H97) -> 5.7142857 | E2: =AVERAGE('PQ Audit Checklist'!I7,'PQ Audit Checklist'!I13,'PQ Audit Checklist'!I19,'PQ Audit Checklist'!I25,'PQ Audit Checklist'!I31,'PQ Audit Checklist'!I37,'PQ Audit Checklist'!I43,'PQ Audit Checklist'!I49,'PQ Audit Checklist'!I55,'PQ Audit Checklist'!I61,'PQ Audit Checklist'!I67,'PQ Audit Checklist'!I73:I79,'PQ Audit Checklist'!I73,'PQ Audit Checklist'!I85,'PQ Audit Checklist'!I97) -> 6.9047619 | F2: VF6NP Leading | G2: Clear improvement, strong usability execution
B3: Aesthetics | C3: =AVERAGEA('PQ Audit Checklist'!G5,'PQ Audit Checklist'!G11,'PQ Audit Checklist'!G17,'PQ Audit Checklist'!G23,'PQ Audit Checklist'!G29,'PQ Audit Checklist'!G35,'PQ Audit Checklist'!G41,'PQ Audit Checklist'!G47,'PQ Audit Checklist'!G53,'PQ Audit Checklist'!G59,'PQ Audit Checklist'!G65,'PQ Audit Checklist'!G71,'PQ Audit Checklist'!G77,'PQ Audit Checklist'!G83,'PQ Audit Checklist'!G95) -> 6.6666667 | D3: =AVERAGEA('PQ Audit Checklist'!H5,'PQ Audit Checklist'!H11,'PQ Audit Checklist'!H17,'PQ Audit Checklist'!H23,'PQ Audit Checklist'!H29,'PQ Audit Checklist'!H35,'PQ Audit Checklist'!H41,'PQ Audit Checklist'!H47,'PQ Audit Checklist'!H53,'PQ Audit Checklist'!H59,'PQ Audit Checklist'!H65,'PQ Audit Checklist'!H71,'PQ Audit Checklist'!H77,'PQ Audit Checklist'!H83,'PQ Audit Checklist'!H95) -> 5.9333333 | E3: =AVERAGEA('PQ Audit Checklist'!I5,'PQ Audit Checklist'!I11,'PQ Audit Checklist'!I17,'PQ Audit Checklist'!I23,'PQ Audit Checklist'!I29,'PQ Audit Checklist'!I35,'PQ Audit Checklist'!I41,'PQ Audit Checklist'!I47,'PQ Audit Checklist'!I53,'PQ Audit Checklist'!I59,'PQ Audit Checklist'!I65,'PQ Audit Checklist'!I71,'PQ Audit Checklist'!I77,'PQ Audit Checklist'!I83,'PQ Audit Checklist'!I95) -> 7 | F3: VF6NP Leading | G3: Strong design quality and premium perception
B4: Fit & Finish | C4: =AVERAGE('PQ Audit Checklist'!G4,'PQ Audit Checklist'!G10,'PQ Audit Checklist'!G16,'PQ Audit Checklist'!G22,'PQ Audit Checklist'!G28,'PQ Audit Checklist'!G34,'PQ Audit Checklist'!G40,'PQ Audit Checklist'!G46,'PQ Audit Checklist'!G52,'PQ Audit Checklist'!G58,'PQ Audit Checklist'!G64,'PQ Audit Checklist'!G70,'PQ Audit Checklist'!G76,'PQ Audit Checklist'!G82,'PQ Audit Checklist'!G94) -> 6.6 | D4: =AVERAGE('PQ Audit Checklist'!H4,'PQ Audit Checklist'!H10,'PQ Audit Checklist'!H16,'PQ Audit Checklist'!H22,'PQ Audit Checklist'!H28,'PQ Audit Checklist'!H34,'PQ Audit Checklist'!H40,'PQ Audit Checklist'!H46,'PQ Audit Checklist'!H52,'PQ Audit Checklist'!H58,'PQ Audit Checklist'!H64,'PQ Audit Checklist'!H70,'PQ Audit Checklist'!H76,'PQ Audit Checklist'!H82,'PQ Audit Checklist'!H94) -> 5.5333333 | E4: =AVERAGE('PQ Audit Checklist'!I4,'PQ Audit Checklist'!I10,'PQ Audit Checklist'!I16,'PQ Audit Checklist'!I22,'PQ Audit Checklist'!I28,'PQ Audit Checklist'!I34,'PQ Audit Checklist'!I40,'PQ Audit Checklist'!I46,'PQ Audit Checklist'!I52,'PQ Audit Checklist'!I58,'PQ Audit Checklist'!I64,'PQ Audit Checklist'!I70,'PQ Audit Checklist'!I76,'PQ Audit Checklist'!I82,'PQ Audit Checklist'!I94) -> 7.1333333 | F4: VF6NP Strong Leader | G4: Best-in-class execution, major gap closure
B5: Touch & Feel | C5: =AVERAGE('PQ Audit Checklist'!G6,'PQ Audit Checklist'!G12,'PQ Audit Checklist'!G18,'PQ Audit Checklist'!G24,'PQ Audit Checklist'!G30,'PQ Audit Checklist'!G36,'PQ Audit Checklist'!G42,'PQ Audit Checklist'!G48,'PQ Audit Checklist'!G54,'PQ Audit Checklist'!G60,'PQ Audit Checklist'!G66,'PQ Audit Checklist'!G72,'PQ Audit Checklist'!G78,'PQ Audit Checklist'!G84,'PQ Audit Checklist'!G96) -> 6.6666667 | D5: =AVERAGE('PQ Audit Checklist'!H6,'PQ Audit Checklist'!H12,'PQ Audit Checklist'!H18,'PQ Audit Checklist'!H24,'PQ Audit Checklist'!H30,'PQ Audit Checklist'!H36,'PQ Audit Checklist'!H42,'PQ Audit Checklist'!H48,'PQ Audit Checklist'!H54,'PQ Audit Checklist'!H60,'PQ Audit Checklist'!H66,'PQ Audit Checklist'!H72,'PQ Audit Checklist'!H78,'PQ Audit Checklist'!H84,'PQ Audit Checklist'!H96) -> 5.8 | E5: =AVERAGE('PQ Audit Checklist'!I6,'PQ Audit Checklist'!I12,'PQ Audit Checklist'!I18,'PQ Audit Checklist'!I24,'PQ Audit Checklist'!I30,'PQ Audit Checklist'!I36,'PQ Audit Checklist'!I42,'PQ Audit Checklist'!I48,'PQ Audit Checklist'!I54,'PQ Audit Checklist'!I60,'PQ Audit Checklist'!I66,'PQ Audit Checklist'!I72,'PQ Audit Checklist'!I78,'PQ Audit Checklist'!I84,'PQ Audit Checklist'!I96) -> 6.3333333 | F5: BYD Leading | G5: Noticeable gap in tactile density and refinement
B6: Sound Quality | C6: =AVERAGE('PQ Audit Checklist'!G8,'PQ Audit Checklist'!G14,'PQ Audit Checklist'!G20,'PQ Audit Checklist'!G26,'PQ Audit Checklist'!G32,'PQ Audit Checklist'!G38,'PQ Audit Checklist'!G44,'PQ Audit Checklist'!G50,'PQ Audit Checklist'!G56,'PQ Audit Checklist'!G62,'PQ Audit Checklist'!G68,'PQ Audit Checklist'!G74,'PQ Audit Checklist'!G80,'PQ Audit Checklist'!G86,'PQ Audit Checklist'!G98) -> 6.1333333 | D6: =AVERAGE('PQ Audit Checklist'!H8,'PQ Audit Checklist'!H14,'PQ Audit Checklist'!H20,'PQ Audit Checklist'!H26,'PQ Audit Checklist'!H32,'PQ Audit Checklist'!H38,'PQ Audit Checklist'!H44,'PQ Audit Checklist'!H50,'PQ Audit Checklist'!H56,'PQ Audit Checklist'!H62,'PQ Audit Checklist'!H68,'PQ Audit Checklist'!H74,'PQ Audit Checklist'!H80,'PQ Audit Checklist'!H86,'PQ Audit Checklist'!H98) -> 5.7333333 | E6: =AVERAGE('PQ Audit Checklist'!I8,'PQ Audit Checklist'!I14,'PQ Audit Checklist'!I20,'PQ Audit Checklist'!I26,'PQ Audit Checklist'!I32,'PQ Audit Checklist'!I38,'PQ Audit Checklist'!I44,'PQ Audit Checklist'!I50,'PQ Audit Checklist'!I56,'PQ Audit Checklist'!I62,'PQ Audit Checklist'!I68,'PQ Audit Checklist'!I74,'PQ Audit Checklist'!I80,'PQ Audit Checklist'!I86,'PQ Audit Checklist'!I98) -> 6.1333333 | F6: BYD = VF6NP | G6: Acceptable but no differentiation
B7: Harmony & Authenticity | C7: =AVERAGE('PQ Audit Checklist'!G9,'PQ Audit Checklist'!G15,'PQ Audit Checklist'!G21,'PQ Audit Checklist'!G27,'PQ Audit Checklist'!G33,'PQ Audit Checklist'!G39,'PQ Audit Checklist'!G45,'PQ Audit Checklist'!G51,'PQ Audit Checklist'!G57,'PQ Audit Checklist'!G63,'PQ Audit Checklist'!G69,'PQ Audit Checklist'!G75,'PQ Audit Checklist'!G81,'PQ Audit Checklist'!G87,'PQ Audit Checklist'!G99) -> 6.7333333 | D7: =AVERAGE('PQ Audit Checklist'!H9,'PQ Audit Checklist'!H15,'PQ Audit Checklist'!H21,'PQ Audit Checklist'!H27,'PQ Audit Checklist'!H33,'PQ Audit Checklist'!H39,'PQ Audit Checklist'!H45,'PQ Audit Checklist'!H51,'PQ Audit Checklist'!H57,'PQ Audit Checklist'!H63,'PQ Audit Checklist'!H69,'PQ Audit Checklist'!H75,'PQ Audit Checklist'!H81,'PQ Audit Checklist'!H87,'PQ Audit Checklist'!H99) -> 6 | E7: =AVERAGE('PQ Audit Checklist'!I9,'PQ Audit Checklist'!I15,'PQ Audit Checklist'!I21,'PQ Audit Checklist'!I27,'PQ Audit Checklist'!I33,'PQ Audit Checklist'!I39,'PQ Audit Checklist'!I45,'PQ Audit Checklist'!I51,'PQ Audit Checklist'!I57,'PQ Audit Checklist'!I63,'PQ Audit Checklist'!I69,'PQ Audit Checklist'!I75,'PQ Audit Checklist'!I81,'PQ Audit Checklist'!I87,'PQ Audit Checklist'!I99) -> 6.9333333 | F7: VF6NP Leading | G7: Strong improvement in brand consistency
B8: Average | C8: =AVERAGE(C2:C7) -> 6.5857143 | D8: =AVERAGE(D2:D7) -> 5.7857143 | E8: =AVERAGE(E2:E7) -> 6.7396825 | F8: VF6NP Leading | G8: Overall competitive position achieved
B11: Exterior | C11: BYD | D11: VF6 | E11: VF6NP | F11: Competitive Position | G11: Assessment
B12: Functionality | C12: =AVERAGE('PQ Audit Checklist'!G7,'PQ Audit Checklist'!G13,'PQ Audit Checklist'!G19,'PQ Audit Checklist'!G25,'PQ Audit Checklist'!G31,'PQ Audit Checklist'!G37) -> 5.8333333 | D12: =AVERAGE('PQ Audit Checklist'!H7,'PQ Audit Checklist'!H13,'PQ Audit Checklist'!H19,'PQ Audit Checklist'!H25,'PQ Audit Checklist'!H31,'PQ Audit Checklist'!H37) -> 6 | E12: =AVERAGE('PQ Audit Checklist'!I7,'PQ Audit Checklist'!I13,'PQ Audit Checklist'!I19,'PQ Audit Checklist'!I25,'PQ Audit Checklist'!I31,'PQ Audit Checklist'!I37) -> 6.1666667 | F12: VF6NP Leading | G12: Clear improvement in usability and functional execution
B13: Aesthetics | C13: =AVERAGE('PQ Audit Checklist'!G5,'PQ Audit Checklist'!G11,'PQ Audit Checklist'!G17,'PQ Audit Checklist'!G23,'PQ Audit Checklist'!G29,'PQ Audit Checklist'!G35) -> 6 | D13: =AVERAGE('PQ Audit Checklist'!H5,'PQ Audit Checklist'!H11,'PQ Audit Checklist'!H17,'PQ Audit Checklist'!H23,'PQ Audit Checklist'!H29,'PQ Audit Checklist'!H35) -> 5.8333333 | E13: =AVERAGE('PQ Audit Checklist'!I5,'PQ Audit Checklist'!I11,'PQ Audit Checklist'!I17,'PQ Audit Checklist'!I23,'PQ Audit Checklist'!I29,'PQ Audit Checklist'!I35) -> 6.5 | F13: VF6NP Leading | G13: Strong design refinement
B14: Fit & Finish | C14: =AVERAGE('PQ Audit Checklist'!G10,'PQ Audit Checklist'!G16,'PQ Audit Checklist'!G22,'PQ Audit Checklist'!G28,'PQ Audit Checklist'!G34,'PQ Audit Checklist'!G4) -> 5.8333333 | D14: =AVERAGE('PQ Audit Checklist'!H10,'PQ Audit Checklist'!H16,'PQ Audit Checklist'!H22,'PQ Audit Checklist'!H28,'PQ Audit Checklist'!H34,'PQ Audit Checklist'!H4) -> 5.1666667 | E14: =AVERAGE('PQ Audit Checklist'!I10,'PQ Audit Checklist'!I16,'PQ Audit Checklist'!I22,'PQ Audit Checklist'!I28,'PQ Audit Checklist'!I34,'PQ Audit Checklist'!I4) -> 5.8333333 | F14: BYD = VF6NP | G14: Meet CN OEM level of gap & flush target
B15: Touch & Feel | C15: =AVERAGE('PQ Audit Checklist'!G6,'PQ Audit Checklist'!G12,'PQ Audit Checklist'!G18,'PQ Audit Checklist'!G24,'PQ Audit Checklist'!G30,'PQ Audit Checklist'!G36) -> 6 | D15: =AVERAGE('PQ Audit Checklist'!H6,'PQ Audit Checklist'!H12,'PQ Audit Checklist'!H18,'PQ Audit Checklist'!H24,'PQ Audit Checklist'!H30,'PQ Audit Checklist'!H36) -> 5.5 | E15: =AVERAGE('PQ Audit Checklist'!I6,'PQ Audit Checklist'!I12,'PQ Audit Checklist'!I18,'PQ Audit Checklist'!I24,'PQ Audit Checklist'!I30,'PQ Audit Checklist'!I36) -> 5.6666667 | F15: BYD Leading | G15: Tactile quality still weaker vs benchmark ( Door closing)
B16: Sound Quality | C16: =AVERAGE('PQ Audit Checklist'!G8,'PQ Audit Checklist'!G14,'PQ Audit Checklist'!G20,'PQ Audit Checklist'!G26,'PQ Audit Checklist'!G32,'PQ Audit Checklist'!G38) -> 6 | D16: =AVERAGE('PQ Audit Checklist'!H8,'PQ Audit Checklist'!H14,'PQ Audit Checklist'!H20,'PQ Audit Checklist'!H26,'PQ Audit Checklist'!H32,'PQ Audit Checklist'!H38) -> 5.6666667 | E16: =AVERAGE('PQ Audit Checklist'!I8,'PQ Audit Checklist'!I14,'PQ Audit Checklist'!I20,'PQ Audit Checklist'!I26,'PQ Audit Checklist'!I32,'PQ Audit Checklist'!I38) -> 5.8333333 | F16: BYD Leading | G16: Acoustic feedback not yet competitive (Door closing)
B17: Harmony & Authenticity | C17: =AVERAGE('PQ Audit Checklist'!G9,'PQ Audit Checklist'!G15,'PQ Audit Checklist'!G21,'PQ Audit Checklist'!G27,'PQ Audit Checklist'!G33,'PQ Audit Checklist'!G39) -> 6 | D17: =AVERAGE('PQ Audit Checklist'!H9,'PQ Audit Checklist'!H15,'PQ Audit Checklist'!H21,'PQ Audit Checklist'!H27,'PQ Audit Checklist'!H33,'PQ Audit Checklist'!H39) -> 6 | E17: =AVERAGE('PQ Audit Checklist'!I9,'PQ Audit Checklist'!I15,'PQ Audit Checklist'!I21,'PQ Audit Checklist'!I27,'PQ Audit Checklist'!I33,'PQ Audit Checklist'!I39) -> 6.3333333 | F17: VF6NP Leading | G17: Improved design consistency and brand alignment
B18: Average | C18: =AVERAGE(C12:C17) -> 5.9444444 | D18: =AVERAGE(D12:D17) -> 5.6944444 | E18: =AVERAGE(E12:E17) -> 6.0555556 | F18: VF6NP Leading | G18: Overall competitive position achieved
B21: Interior | C21: BYD | D21: VF6 | E21: VF6NP | F21: Competitive Position | G21: Assessment
B22: Functionality | C22: =AVERAGE('PQ Audit Checklist'!G43,'PQ Audit Checklist'!G49,'PQ Audit Checklist'!G55,'PQ Audit Checklist'!G61,'PQ Audit Checklist'!G67,'PQ Audit Checklist'!G73,'PQ Audit Checklist'!G79,'PQ Audit Checklist'!G85,'PQ Audit Checklist'!G97) -> 7 | D22: =AVERAGE('PQ Audit Checklist'!H43,'PQ Audit Checklist'!H49,'PQ Audit Checklist'!H55,'PQ Audit Checklist'!H61,'PQ Audit Checklist'!H67,'PQ Audit Checklist'!H73,'PQ Audit Checklist'!H79,'PQ Audit Checklist'!H85,'PQ Audit Checklist'!H97) -> 5.3333333 | E22: =AVERAGE('PQ Audit Checklist'!I43,'PQ Audit Checklist'!I49,'PQ Audit Checklist'!I55,'PQ Audit Checklist'!I61,'PQ Audit Checklist'!I67,'PQ Audit Checklist'!I73,'PQ Audit Checklist'!I79,'PQ Audit Checklist'!I85,'PQ Audit Checklist'!I97) -> 7.3333333 | F22: VF6NP Leading | G22: Significant usability and packaging improvement
B23: Aesthetics | C23: =AVERAGE('PQ Audit Checklist'!G41,'PQ Audit Checklist'!G47,'PQ Audit Checklist'!G53,'PQ Audit Checklist'!G59,'PQ Audit Checklist'!G65,'PQ Audit Checklist'!G71,'PQ Audit Checklist'!G77,'PQ Audit Checklist'!G83,'PQ Audit Checklist'!G95) -> 7.1111111 | D23: =AVERAGE('PQ Audit Checklist'!H41,'PQ Audit Checklist'!H47,'PQ Audit Checklist'!H53,'PQ Audit Checklist'!H59,'PQ Audit Checklist'!H65,'PQ Audit Checklist'!H71,'PQ Audit Checklist'!H77,'PQ Audit Checklist'!H83,'PQ Audit Checklist'!H95) -> 6 | E23: =AVERAGE('PQ Audit Checklist'!I41,'PQ Audit Checklist'!I47,'PQ Audit Checklist'!I53,'PQ Audit Checklist'!I59,'PQ Audit Checklist'!I65,'PQ Audit Checklist'!I71,'PQ Audit Checklist'!I77,'PQ Audit Checklist'!I83,'PQ Audit Checklist'!I95) -> 7.3333333 | F23: VF6NP Leading | G23: Strong premium perception through design execution
B24: Fit & Finish | C24: =AVERAGE('PQ Audit Checklist'!G40,'PQ Audit Checklist'!G46,'PQ Audit Checklist'!G52,'PQ Audit Checklist'!G58,'PQ Audit Checklist'!G64,'PQ Audit Checklist'!G70,'PQ Audit Checklist'!G76,'PQ Audit Checklist'!G82,'PQ Audit Checklist'!G94) -> 7.1111111 | D24: =AVERAGE('PQ Audit Checklist'!H40,'PQ Audit Checklist'!H46,'PQ Audit Checklist'!H52,'PQ Audit Checklist'!H58,'PQ Audit Checklist'!H64,'PQ Audit Checklist'!H70,'PQ Audit Checklist'!H76,'PQ Audit Checklist'!H82,'PQ Audit Checklist'!H94) -> 5.7777778 | E24: =AVERAGE('PQ Audit Checklist'!I40,'PQ Audit Checklist'!I46,'PQ Audit Checklist'!I52,'PQ Audit Checklist'!I58,'PQ Audit Checklist'!I64,'PQ Audit Checklist'!I70,'PQ Audit Checklist'!I76,'PQ Audit Checklist'!I82,'PQ Audit Checklist'!I94) -> 8 | F24: VF6NP Strong Leader | G24: Best-in-class execution, major improvement vs VF6
B25: Touch & Feel | C25: =AVERAGE('PQ Audit Checklist'!G42,'PQ Audit Checklist'!G48,'PQ Audit Checklist'!G54,'PQ Audit Checklist'!G60,'PQ Audit Checklist'!G66,'PQ Audit Checklist'!G72,'PQ Audit Checklist'!G78,'PQ Audit Checklist'!G84,'PQ Audit Checklist'!G96) -> 7.1111111 | D25: =AVERAGE('PQ Audit Checklist'!H42,'PQ Audit Checklist'!H48,'PQ Audit Checklist'!H54,'PQ Audit Checklist'!H60,'PQ Audit Checklist'!H66,'PQ Audit Checklist'!H72,'PQ Audit Checklist'!H78,'PQ Audit Checklist'!H84,'PQ Audit Checklist'!H96) -> 6 | E25: =AVERAGE('PQ Audit Checklist'!I42,'PQ Audit Checklist'!I48,'PQ Audit Checklist'!I54,'PQ Audit Checklist'!I60,'PQ Audit Checklist'!I66,'PQ Audit Checklist'!I72,'PQ Audit Checklist'!I78,'PQ Audit Checklist'!I84,'PQ Audit Checklist'!I96) -> 6.7777778 | F25: BYD Leading | G25: Still lacking density and tactile refinement
B26: Sound Quality | C26: =AVERAGE('PQ Audit Checklist'!G44,'PQ Audit Checklist'!G50,'PQ Audit Checklist'!G56,'PQ Audit Checklist'!G62,'PQ Audit Checklist'!G68,'PQ Audit Checklist'!G74,'PQ Audit Checklist'!G80,'PQ Audit Checklist'!G86,'PQ Audit Checklist'!G98) -> 6.2222222 | D26: =AVERAGE('PQ Audit Checklist'!H44,'PQ Audit Checklist'!H50,'PQ Audit Checklist'!H56,'PQ Audit Checklist'!H62,'PQ Audit Checklist'!H68,'PQ Audit Checklist'!H74,'PQ Audit Checklist'!H80,'PQ Audit Checklist'!H86,'PQ Audit Checklist'!H98) -> 5.7777778 | E26: =AVERAGE('PQ Audit Checklist'!I44,'PQ Audit Checklist'!I50,'PQ Audit Checklist'!I56,'PQ Audit Checklist'!I62,'PQ Audit Checklist'!I68,'PQ Audit Checklist'!I74,'PQ Audit Checklist'!I80,'PQ Audit Checklist'!I86,'PQ Audit Checklist'!I98) -> 6.3333333 | F26: Slight VF6NP Leading | G26: Minor improvement, but not a differentiator
B27: Harmony & Authenticity | C27: =AVERAGE('PQ Audit Checklist'!G45,'PQ Audit Checklist'!G51,'PQ Audit Checklist'!G57,'PQ Audit Checklist'!G63,'PQ Audit Checklist'!G69,'PQ Audit Checklist'!G75,'PQ Audit Checklist'!G81,'PQ Audit Checklist'!G87,'PQ Audit Checklist'!G99) -> 7.2222222 | D27: =AVERAGE('PQ Audit Checklist'!H45,'PQ Audit Checklist'!H51,'PQ Audit Checklist'!H57,'PQ Audit Checklist'!H63,'PQ Audit Checklist'!H69,'PQ Audit Checklist'!H75,'PQ Audit Checklist'!H81,'PQ Audit Checklist'!H87,'PQ Audit Checklist'!H99) -> 6 | E27: =AVERAGE('PQ Audit Checklist'!I45,'PQ Audit Checklist'!I51,'PQ Audit Checklist'!I57,'PQ Audit Checklist'!I63,'PQ Audit Checklist'!I69,'PQ Audit Checklist'!I75,'PQ Audit Checklist'!I81,'PQ Audit Checklist'!I87,'PQ Audit Checklist'!I99) -> 7.3333333 | F27: VF6NP Leading | G27: Strong brand consistency and design coherence
B28: Average | C28: =AVERAGE(C22:C27) -> 6.962963 | D28: =AVERAGE(D22:D27) -> 5.8148148 | E28: =AVERAGE(E22:E27) -> 7.1851852 | F28: VF6NP Leading | G28: Clear competitive advantage achieved
B31: Modules | C31: BYD | D31: VF6 | E31: VF6NP | F31: Competitive Position | G31: Assessment
B32: Body | C32: =AVERAGE('PQ Audit Checklist'!G4:G9) -> 6 | D32: =AVERAGE('PQ Audit Checklist'!H4:H9) -> 5.6666667 | E32: =AVERAGE('PQ Audit Checklist'!I4:I9) -> 5.6666667 | F32: BYD Leading | G32: Surface quality and overall execution still weaker
B33: Doors & Closures | C33: =AVERAGE('PQ Audit Checklist'!M10:M15) -> 6 | D33: =AVERAGE('PQ Audit Checklist'!N10:N15) -> 5.5 | E33: =AVERAGE('PQ Audit Checklist'!O10:O15) -> 5.8333333 | F33: Slight BYD Leading | G33: Improved but still lacking closing feel and precision
B34: Lighting | C34: =AVERAGEA('PQ Audit Checklist'!G16:G21) -> 6 | D34: =AVERAGEA('PQ Audit Checklist'!H16:H21) -> 5.8333333 | E34: =AVERAGEA('PQ Audit Checklist'!I16:I21) -> 6.5 | F34: VF6NP Leading | G34: Strong visual quality and perceived innovation
B35: Glass & Wiper | C35: =AVERAGE('PQ Audit Checklist'!G22:G27) -> 5.6666667 | D35: =AVERAGE('PQ Audit Checklist'!H22:H27) -> 5.6666667 | E35: =AVERAGE('PQ Audit Checklist'!I22:I27) -> 5.6666667 | F35: BYD = VF6NP | G35: No differentiation, baseline level
B36: Exterior Trim | C36: =AVERAGE('PQ Audit Checklist'!G28:G33) -> 6 | D36: =AVERAGE('PQ Audit Checklist'!H28:H33) -> 5.5 | E36: =AVERAGE('PQ Audit Checklist'!I28:I33) -> 6.3333333 | F36: VF6NP Leading | G36: Improved material and visual execution
B37: Wheel/Wheel cover /Rim | C37: =AVERAGE('PQ Audit Checklist'!G34:G39) -> 6 | D37: =AVERAGE('PQ Audit Checklist'!H34:H39) -> 6 | E37: =AVERAGE('PQ Audit Checklist'!I34:I39) -> 6.3333333 | F37: VF6NP Leading | G37: Better design and visual impact
B38: Instrument Panel | C38: =AVERAGE('PQ Audit Checklist'!G40:G45) -> 7 | D38: =AVERAGE('PQ Audit Checklist'!H40:H45) -> 5.5 | E38: =AVERAGE('PQ Audit Checklist'!I40:I45) -> 8 | F38: VF6NP Strong Leader | G38: Best-in-class execution and premium perception
B39: Steering Wheel | C39: =AVERAGE('PQ Audit Checklist'!G46:G51) -> 7 | D39: =AVERAGE('PQ Audit Checklist'!H46:H51) -> 6.5 | E39: =AVERAGE('PQ Audit Checklist'!I46:I51) -> 7.3333333 | F39: VF6NP Leading | G39: Good improvement in tactile and design quality
B40: Console | C40: =AVERAGE('PQ Audit Checklist'!G52:G57) -> 7 | D40: =AVERAGE('PQ Audit Checklist'!H52:H57) -> 5.3333333 | E40: =AVERAGE('PQ Audit Checklist'!I52:I57) -> 7.5 | F40: VF6NP Strong Leader | G40: Major improvement in usability and perceived quality
B41: Door Trim | C41: =AVERAGE('PQ Audit Checklist'!G58:G63) -> 7.1666667 | D41: =AVERAGE('PQ Audit Checklist'!H58:H63) -> 5.5 | E41: =AVERAGE('PQ Audit Checklist'!I58:I63) -> 7.5 | F41: VF6NP Leading | G41: Strong material and design execution
B42: Seats | C42: =AVERAGE('PQ Audit Checklist'!G64:G69) -> 7.3333333 | D42: =AVERAGE('PQ Audit Checklist'!H64:H69) -> 6 | E42: =AVERAGE('PQ Audit Checklist'!I64:I69) -> 7.5 | F42: VF6NP Leading | G42: Comfort and perceived quality improved
B43: HVAC | C43: =AVERAGE('PQ Audit Checklist'!G70:G75) -> 7.1666667 | D43: =AVERAGE('PQ Audit Checklist'!H70:H75) -> 5.8333333 | E43: =AVERAGE('PQ Audit Checklist'!I70:I75) -> 7.5 | F43: VF6NP Leading | G43: Improved usability and integration
B44: Infotainment | C44: =AVERAGE('PQ Audit Checklist'!G76:G81) -> 6.8333333 | D44: =AVERAGE('PQ Audit Checklist'!H76:H81) -> 5.8333333 | E44: =AVERAGE('PQ Audit Checklist'!I76:I81) -> 6.3333333 | F44: BYD Leading | G44: Screen size and resolution imrprovement required
B45: Interior Lighting | C45: =AVERAGE('PQ Audit Checklist'!G82:G87) -> 7.1666667 | D45: =AVERAGE('PQ Audit Checklist'!H82:H87) -> 5.8333333 | E45: =AVERAGE('PQ Audit Checklist'!I82:I87) -> 6.3333333 | F45: BYD Leading | G45: Ambient quality and refinement required
B46: Key & Entry | C46: =AVERAGE('PQ Audit Checklist'!G94:G99) -> 6 | D46: =AVERAGE('PQ Audit Checklist'!H94:H99) -> 6 | E46: =AVERAGE('PQ Audit Checklist'!I94:I99) -> 6.6666667 | F46: VF6NP Leading | G46: Improved usability and perceived convenience
B47: Average | C47: =AVERAGE(C32:C46) -> 6.5555556 | D47: =AVERAGE(D32:D46) -> 5.7666667 | E47: =AVERAGE(E32:E46) -> 6.7333333 | F47: VF6NP Leading | G47: Overall competitive position achieved

Sheet Must_Want Fix 
B3: 🔳 Must Fix / Want Fix Key Criteria
B5: No | C5: Category | D5: Must Fix | E5: Want Fix | F5: PQ Criteria
B6: 1 | C6: Customer Perception | D6: Clearly visible, audible, or tactile defect recognized by most customers at first interaction | E6: Not noticeable under normal usage or only detectable under special condition | F6: Aesthetics / Sound / Touch & Feel
B7: 2 | C7: A&U (Usage & Ergonomics) | D7: Requires body lean, awkward posture, excessive reach, or repeated inconvenience in daily use | E7: Usable within normal posture with minor or occasional inconvenience | F7: Functionality / Harmony & Authenticity
B8: 3 | C8: GD&T / Quality Level | D8: Out of DTS tolerance OR visible gap/flush inconsistency OR multiple occurrences (systematic issue) | E8: Within DTS tolerance AND isolated issue with no visible inconsistency | F8: Fit & Finish
B9: 4 | C9: Brand & Design Integrity | D9: Breaks design intent (cutline, symmetry, alignment) OR visible in key (Zone A) areas OR creates cheap/inconsistent perception | E9: Low visibility area AND no impact on overall design harmony | F9: Aesthetics / Harmony & Authenticity
B10: 5 | C10: System Impact | D10: Causes secondary issues (Squeak & rattle) OR linked to known field/warranty issue | E10: No cross-system impact AND no history of field issue | F10: Functionality / Sound Quality
B12: 🔳 Operational Rules
B14: No | C14: Rule | D14: Description
B15: 1 | C15: Classification Discipline | D15: All issues must follow Must Fix / Want Fix definition
B16: 2 | C16: Must Fix Timing | D16: Must Fix issues must be resolved before PTO Gate (PR release)
B17: 3 | C17: Exception Handling | D17: If not resolved, approved ICA/PCA with clear plan is required
B18: 4 | C18: Gate Opening Condition | D18: Gate can open only if no open Must Fix OR ICA/PCA is approved
B19: 5 | C19: Implementation Commitment | D19: All Must Fix issues must be implemented and verified by PTO
B20: 6 | C20: Want Fix Control | D20: Only acceptable if below perception threshold and no impact on safety/function/brand
B21: 7 | C21: Escalation Rule | D21: If a Must Fix issue is not aligned for resolution across teams, it must be escalated to DCEO level for final decision

Sheet RPN
B1: 1. RPN
B2: Effect | C2: Criteria: Severity of Effect on Product (Customer Effect) | F2: Rank | G2: Classification | I2: Likelihood of Failure | J2: Criteria: Occurrence of Cause - DFMEA (Design life/reliability of item/vehicle) | L2: Criteria: Occurrence of Cause - DFMEA (Incidents per items/vehicles) | M2: Rank | O2: Opportunity for Detection | P2: Criteria: Likelihood of Detection by Design Control | R2: Rank | S2: Likelihood of Detection
B3: Failure to Meet Safety and/or Regulatory Requirements | C3: Potential failure mode affects safe vehicle operation and/or involves noncompliance with government regulation without warning | F3: 10 | G3: <CC> | I3: Very High | J3: New technology/new design with no history. | L3: ≥ 100 per thousand ≥ 1 in 10 | M3: 10 | O3: No detection opportunity | P3: No current design control; Cannot detect or is not analyzed. | R3: 10 | S3: Almost Impossible
C4: Potential failure mode affects safe vehicle operation and/or involves noncompliance with government regulation with warning | F4: 9 | I4: High | J4: Failure is inevitable with new design, new application, or change in duty cycle/operating conditions. | L4: 50 per thousand 1 in 20 | M4: 9 | O4: Not likely to detect at any stage | P4: Design analysis/detection controls have a weak detection capability; Virtual Analysis (e.g., CAE, FEA, etc.) is not correlated to expected actual operating conditions. | R4: 9 | S4: Very Remote
B5: Loss or Degradation of Primary Function | C5: Loss of primary function (vehicle inoperable, does not affect safe vehicle operation). | F5: 8 | G5: <SC> | J5: Failure is likely with new design, new application, or change in duty cycle/operating conditions. | L5: 20 per thousand 1 in 50 | M5: 8 | O5: Post Design Freeze and prior to launch | P5: Product verification/validation after design freeze and prior to launch with pass/fail testing (Subsystem or system testing with acceptance criteria such as ride and handling, shipping evaluation, etc.) | R5: 8 | S5: Remote
C6: Degradation of primary function (vehicle operable, but at reduced level of performance) | F6: 7 | J6: Failure is uncertain with new design, new application, or change in duty cycle/operating conditions. | L6: 10 per thousand 1 in 100 | M6: 7 | P6: Product verification/validation after design freeze and prior to launch with test to failure testing (Subsystem or system testing until failure occurs, testing of system interactions, etc.) | R6: 7 | S6: Very Low
B7: Loss or Degradation of Secondaty Function | C7: Loss of secondary function (vehicle operable, but comfort / convenience functions inoperable). | F7: 6 | G7: <HIC> | I7: Moderate | J7: Frequent failures associated with similar designs or in design simulation and testing. | L7: 2 per thousand 1 in 500 | M7: 6 | P7: Product verification/validation after design freeze and prior to launch with degradation testing (Subsystem or system testing after durability test, e.g., function check). | R7: 6 | S7: Low
C8: Degradation of secondary function (vehicle operable, but comfort / convenience functions at reduced level of performance). | F8: 5 | J8: Occasional failures associated with similar designs or in design simulation and testing. | L8: .5 per thousand 1 in 2,000 | M8: 5 | O8: Prior to Design Freeze | P8: Product validation (reliability testing, development or validation tests) prior to design freeze using pass/fail testing (e.g., acceptance criteria for performance, functions checks, etc.). | R8: 5 | S8: Moderate
B9: Annoyance | C9: Appearance or Audible Noise, vehicle operable, item does not conform and noticed by most customers (> 75%). | F9: 4 | G9: <STD> | J9: Isolated failures associated with similar designs or in design simulation and testing. | L9: .1 per thousand 1 in 10,000 | M9: 4 | P9: Product validation (reliability testing, development or validation tests) prior to design freeze using test to failure (e.g., until leaks, yields, cracks, etc.). | R9: 4 | S9: Moderately High
C10: Appearance or Audible Noise, vehicle operable, item does not conform and noticed by many customers (> 50%). | F10: 3 | I10: Low | J10: Only isolated failures associated with almost identical design or in design simulation and testing | L10: .01 per thousand 1 in 100,000 | M10: 3 | P10: Product validation (reliability testing, development or validation tests) prior to design freeze using degradation testing (e.g., data trends, before/after values, etc.). | R10: 3 | S10: High
C11: Appearance or Audible Noise, vehicle operable, item does not conform and noticed by discriminating customers (> 25%). | F11: 2 | J11: No observed failures associated with almost identical design or in design simulation and testing | L11: ≤.001 per thousand 1 in 1,000,000 | M11: 2 | O11: Virtual Analysis - Correlated | P11: Design analysis/detection controls have a strong detection capability; Virtual Analysis (e.g., CAE, FEA, etc.) is highly correlated with actual or expected operating conditions perior to design freeze. | R11: 2 | S11: Very High
B12: No effect | C12: No discernible effect | F12: 1 | I12: Very Low | J12: Failure is eliminated though preventive control. | L12: Failure is eliminated through preventive control | M12: 1 | O12: Detection not applicable; Failure Prevention | P12: Failure cause or failure mode can not occur because it is fully prevented through design solutions (e.g., proven design standard, best prectice or common material, etc.). | R12: 1 | S12: Almost Certain
B13: *Severity, Occurrence and Detection tables from AIAG FMEA 4th edition 2008 version
B15: 2. Key product characteristics - follow VFDST00010100_Special Characteristics Class Designation
B17: Classification Symbols | C17: Severity | D17: Abbreviation | E17: Details
B18: <CC> | C18: 10, 9 | D18: Critical Characteristics | E18: Function related to Safety & Homologation & Regulation
B19: <SC> | C19: 8, 7 | D19: Significant Characteristics | E19: Directly related to the Reliability or external Customer satisfaction and Product Performance or Product primary functions. Product characteristics which affect the fitting, the function, the performance of the further processing of the product (Buildability).
B20: <HIC> | C20: 6, 5 | D20: High Importance Characteristics | E20: Product secondary functions and Process or improper Manufacturing/Assembly
B21: <STD> | C21: 4, 3, 2, 1 | D21: Standard Characteristics | E21: All others Standard characteristics

Sheet PHC Gate report
B2: TA PHC Gateway open contents
B3: Criteria | C3: Status | D3: Conclusion | E3: Explanation
B4: Target Definition (VTS) | C4: Aligned | D4: Pass | E4: B-Class CAS PQ audit confirms that program target direction is aligned with PALS & VTS targets at Competitive level.
B5: Benchmark Reference | C5: Aligned | D5: Pass | E5: VTS targets are benchmark-driven.
B6: Lessons Learned Integration | C6: Applied | D6: Pass | E6: Lessons learned have been fully integrated into engineering direction.
B7: Design Convergence (B-Class) | C7: Controlled | D7: Pass | E7: Design convergence is under control and progressing toward defined PQ targets.
B8: Initial DTS Target Set | C8: Controlled | D8: Pass | E8: Initial DTS targets are defined and aligned with PQ requirements.
B9: Attatchments | C9: Lessons & leant implement report
C10: Benchmakring report with PALS/VTS target set
C11: Desing convergence B Class PQ status
B13: FC PHC Gateway open contents
B14: Criteria | C14: Status | D14: Conclusion | E14: Explanation
B15: Must-Fix Issues | C15: None | D15: Pass | E15: No Must-Fix issues remaining.
B16: Customer-visible critical issues | C16: None | D16: Pass | E16: No critical issues impacting customer perception have been identified.
B17: PQ Target (PALS / VTS) | C17: Achieved | D17: Pass | E17: A-Class CAS PQ audit confirms that VF5NP meets PALS & VTS targets at Competitive level.
B18: Open Issues Risk | C18: Controlled | D18: Pass | E18: All remaining issues are non-blocking and under control.
B19: Final DTS Target Release | C19: Achieved | D19: Pass | E19: Final DTS targets are released and validated.
B20: Attatchments | C20: FC gate PQ report
C21: Desing convergence A Class PQ status
C22: Lessons & leant implement report
B23: PTO PHC Gateway open contents
B24: Criteria | C24: Status | D24: Conclusion | E24: Explanation
B25: Must-Fix Issues | C25: None | D25: Pass | E25: No Must-Fix issues remaining prior to launch.
B26: Customer-visible critical issues | C26: None | D26: Pass | E26: No customer-visible critical issues have been identified.
B27: PQ Target (PALS / VTS) | C27: Achieved | D27: Pass | E27: LS PQ audit confirms that VF5NP meets PALS & VTS targets at Competitive level under near-production conditions.
B28: Open Issues Risk | C28: Controlled | D28: Pass | E28: All remaining issues are minor, non-blocking, and under control.
B29: Attatchments | C29: PTO gate PQ report
C30: PTO Audit report with status
B31: SOP PHC Gateway open contents
B32: Criteria | C32: Status | D32: Conclusion | E32: Explanation
B33: Must-Fix Issues | C33: None | D33: Pass | E33: No Must-Fix issues remaining.
B34: Customer-visible critical issues | C34: None | D34: Pass | E34: No critical issues impacting customer perception have been identified.
B35: PQ Target (PALS / VTS) | C35: Achieved | D35: Pass | E35: LS PQ audit confirms that VF5NP meets PALS & VTS targets at Competitive level in final production quality.
B36: Open Issues Risk | C36: Controlled | D36: Pass | E36: Product quality is stable and ready for customer delivery.
B37: Attatchments | C37: SOP gate PQ report
C38: LS Audit report with status

Sheet Sheet2
C2: PTO / LS / SOP Vehicle Audit RASIC
C4: (ICA/PCA Tracking Ownership Update)**
C6: Activity | D6: Detailed Activity Description | E6: PQ / GD&T / A&U | F6: QE / VCA | G6: PMO / MML | H6: ADV | I6: Remarks
C7: VCA Vehicle Selection | D7: Selection of audit target vehicle variant/spec and confirmation of production sequence | E7: I | F7: R / A | G7: S | H7: I | I7: Ensure specific configurations are included in audit scope
C8: DCR / ECR Tracking | D8: Management of design (DCR) and engineering/process (ECR) change history | E8: S | F8: S | G8: R / A | H8: I | I8: Acts as central hub for all change history
C9: ICA / PCA Tracking | D9: Tracking status of Interim (ICA) and Permanent (PCA) corrective actions | E9: S | F9: S | G9: R / A | H9: I | I9: PMO leads conversion from ICA to PCA before SOP
C10: Vehicle Mapping | D10: Mapping of changes/actions to actual production vehicles (VIN level) | E10: I | F10: S | G10: R / A | H10: I | I10: Identification and mapping of “event vehicles” for audit
C11: Change Notification | D11: Communication of change and action information to VCA and PQ teams | E11: I | F11: S | G11: R / A | H11: I | I11: Official notification for audit preparation
C12: Change Reflection Check | D12: Verification of ICA/PCA implementation on actual vehicles | E12: R / A | F12: S | G12: S | H12: I | I12: PQ verifies physical implementation on vehicle
C13: Joint Audit | D13: Vehicle evaluation based on checklist | E13: R | F13: R / A | G13: I | H13: I | I13: PQ (technical & precision), VCA (final approval)
C14: Audit Report | D14: Summary of audit results and quality rating definition | E14: R | F14: R / A | G14: I | H14: I | I14: Alignment and finalization of evaluation results
C15: JIRA Creation | D15: Registration of detected issues and assignment of ownership | E15: R | F15: R / A | G15: I | H15: I | I15: Technical issue logging and data management
C16: Execution / Fix | D16: Root cause analysis and physical implementation of corrective actions | E16: S | F16: S | G16: R / A | H16: I | I16: PQ directly drives and manages corrective actions
C17: Weekly Tracking | D17: Monitoring of open issues and residual ICA risks | E17: S | F17: S | G17: R / A | H17: I | I17: PMO controls overall progress and status
C18: Closure Validation | D18: Re-verification of improvements and final closure of JIRA issues | E18: S | F18: R / A | G18: S | H18: I | I18: Issue closure after VCA final approval

Sheet Sheet1
C6: Final PTO/LS/SOP Vehicle Audit RASIC (Gate-Aligned & Optimized Version)
C8: No | D8: GATE Phase | E8: Activity | F8: Detailed Activity Description | G8: PQ | H8: QE / QC | I8: VCA | J8: PMO | K8: MML / ADV | L8: Remarks
C9: 1 | D9: Gate Preparation | E9: VCA Vehicle Selection | F9: Selection of audit target vehicle type/spec and confirmation of production sequence | G9: C | H9: R | I9: A | J9: R | K9: S | L9: Prioritize high-risk specs based on PTO issue history
C10: 2 | D10: Gate Preparation | E10: DCR / ECR Tracking | F10: Management of design (DCR) and process (ECR) change history | G10: S | H10: R | I10: S | J10: A | K10: R | L10: Central hub for all change history
C11: 3 | D11: Gate Preparation | E11: ICA / PCA Tracking | F11: Tracking status of interim (ICA) and permanent (PCA) actions | G11: S | H11: R | I11: S | J11: A | K11: R | L11: Manage PCA conversion before SOP
C12: 4 | D12: Gate Preparation | E12: Vehicle Mapping | F12: Mapping of changes/actions to actual production vehicles (VIN level) | G12: I | H12: R | I12: S | J12: A | K12: R | L12: QE/QC confirms and judges DCR/ECR vehicle application status
C13: 5 | D13: Gate Preparation | E13: Change Notification | F13: Notification of changes and actions to VCA / PQ / QE departments | G13: C | H13: C | I13: R | J13: A | K13: S | L13: Formal audit trigger
C14: 6 | D14: Gate Execution | E14: Joint Audit (1st) | F14: Initial vehicle evaluation based on checklist | G14: R | H14: R | I14: R | J14: S | K14: S | L14: PQ leads technical judgment, QE validates actual build & PTO issues
C15: 7 | D15: Gate Execution | E15: Fix Implementation Coordination | F15: Coordination of ICA/PCA/DCR/ECR physical application to vehicle | G15: S | H15: R | I15: S | J15: A | K15: R | L15: Execution by Engineering / In-Plant
C16: 8 | D16: Gate Execution | E16: Change Reflection Check | F16: Verification that all actions are physically reflected on target vehicle | G16: R | H16: R | I16: S | J16: S | K16: S | L16: Mandatory gate before Re-Audit
C17: 9 | D17: Gate Execution | E17: Re-Audit (2nd) | F17: Re-verification of updated vehicle after fix implementation | G17: R | H17: R | I17: A | J17: S | K17: S | L17: VCA performs independent final confirmation
C18: 10 | D18: Gate Decision | E18: Must Fix / Want Fix Decision | F18: Final classification of Must Fix / Want Fix and notification to MML | G18: R | H18: R | I18: R | J18: I | K18: S | L18: PQ + QE/QC recommendation, VCA makes final decision
C19: 11 | D19: Gate Decision | E19: Audit Report | F19: Final audit summary, quality rating, and Must/Want Fix recording | G19: R | H19: R | I19: A | J19: S | K19: S | L19: QE/QC leads PTO issue analysis, VCA makes independent final quality judgment
C20: 12 | D20: Gate Decision | E20: JIRA Creation | F20: Registration of detected issues and assignee assignment (with Must/Want Fix tag) | G20: R | H20: R | I20: R | J20: I | K20: I | L20: QE/QC leads registration of actual vehicle issues
... C22: 14 | D22: Gate Follow-up | E22: Closure Validation | F22: Final confirmation of improvements and JIRA issue closure | G22: S | H22: R | I22: A | J22: S | K22: I | L22: VCA gives final quality approval for closure

Sheet Sheet3
C5: Vinfast | E5: Program | F5: MARKET | G5: Attribute Level 2 | H5: VD DNA Target improvement
C6: Green | D6: Green | E6: MGreen | F6: VN | G6: 1) Simplify cutline | H6: 1) Competitive Fit & Finish (stable, no defect perception)
E7: Herio Green | F7: All | G7: 2) Reduce part counts | H7: 2) Zero noise/loose perception (basic Sound Quality )
E8: Nerio | F8: All | G8: 3) Standardize interface & tolerance | H8: 3) Manufacturing stability (No variation-driven defects)
E9: Limogreen | F9: All | G9: 4) Improve robustness (variation insensitive design) | H9: 4) Cost-efficient PQ (Value perception )
C10: Vinfast | D10: Low Category | E10: VF3 | F10: All | G10: 1) Fit & Finish stability (gap/flush consistency) | H10: 1) Competitive Fit & Finish (No customer complaint level)
G11: 2) Door closing effort & sound tuning | H11: 2) Solid & acceptable door closing sound (No tinny / no hollow)
G12: 3) Basic tactile improvement (no cheap feel) | H12: 3) Eliminate low-quality perception (entry but not cheap)
E13: VF5 | F13: All | G13: 4) Reduce visible defects | H13: 4) Meet Kano Must-be featurse
D14: Mid Category | E14: VF6 | F14: All | G14: 1) Fit & Finish precision (tight & consistent) | H14: 1) Among Leader Fit & Finish (CN/KR OEM level)
G15: 2) Door closing effort & sound refinement | H15: 2) Premium-like door closing feel (damped, confident)
E16: VF7 | F16: All | G16: 3) Touch & Feel improvement (key contact area) | H16: 3) Elevated tactile quality (soft, solid, controlled force)
E17: VF Limo | F17: All | G17: 4) Harmony improvement (design integration) | H17: 4) Harmonized design perception (no mismatch)
E18: VF Wild | F18: VN/INDIA | G18: 5) CMF consistency | H18: 5) CMF → perceived upgrade
D19: High Category | E19: VF8 | F19: All | G19: 1) Precision Fit & Finish (premium tolerance control) | H19: 1) Among Leader ~ Leader Fit & Finish
G20: 2) Door closing sound & effort (luxury tuning) | H20: 2) Premium door closure (deep, heavy, controlled sound)
G21: 3) Advanced Touch & Feel (material + damping) | H21: 3) High-end tactile experience (soft, dense, premium)
G22: 4) Harmony & Authenticity improvment | H22: 4) Strong brand identity coherence
E23: VF9 | F23: All | G23: 5) Sound quality (operation refinement) | H23: 5) No unwanted noise (refined NVH perception)
E24: MPV | F24: All | G24: 6) Feature-function integration (intuitive UX) | H24: 6) Seamless functionality perception
C25: Lac Hong | D25: Luxury Category | E25: LH 800 | F25: VN | G25: 1) Among Leader Fit & Finish | H25: 1) Leader in CMF (benchmark: LX/EQS)
G26: 2) Premium door closure (deep, heavy, controlled sound) | H26: 2) Ultra-premium tactile perception
G27: 3) High-end tactile experience (soft, dense, premium) | H27: 3) Invisible Fit & Finish (perceived perfection)
G28: 4) Strong brand identity coherence | H28: 4) Signature sound identity (brand sound)
G29: 5) No unwanted noise (refined NVH perception) | H29: 5) Emotional luxury experience (Kansei alignment)
E30: LH900 | F30: VN | G30: 6) Seamless functionality perception
C31: Commerical | D31: Cargo Van | E31: Minivan | F31: VN/INDO | G31: 1) Simplify cutline | H31: 1) Competitive Fit & Finish (stable, no defect perception)
D32: EBUS | E32: 6M | F32: VN | G32: 2) Reduce part counts | H32: 2) Zero noise/loose perception (basic Sound Quality )
E33: 8M | F33: VN | G33: 3) Standardize interface & tolerance | H33: 3) Manufacturing stability (No variation-driven defects)
E34: 12M | F34: VN | G34: 4) Improve robustness (variation insensitive design) | H34: 4) Cost-efficient PQ (Value perception )
E35: 12M Coach Bus | F35: ALL
D36: Escooter | E36: Escooter | F36: VN
